Workbook

Sheet Research Tracker
A1: CRYSTAL PALACE TRANSFER RESEARCH TRACKER
B2: Research sample | G2: Still Palace-owned | L2: Departed | Q2: Value coverage
B3: 47 players | G3: =COUNTIF(K11:K57,"Still at Palace*") -> 22 | L3: =COUNTIF(K11:K57,"Sold")+COUNTIF(K11:K57,"Released / Free") -> 25 | Q3: =COUNT(O11:O57) -> 47
B5: First-team permanent arrivals | G5: Includes players currently on loan | L5: Sold or released | Q5: Current value or sale fee
A7: VALUATION EQUATIONS — ALL FINANCIAL FIELDS ARE IN € MILLIONS
A8: VALUE USED Current MV if Palace-owned; Sale Fee if departed | I8: VALUE GAIN / LOSS Value Used − Fee Paid | Q8: RETURN ON FEE Value Gain/Loss ÷ Fee Paid | Y8: PERFORMANCE FORMULAS Min/Season, efficiency and rating average
A10: Player | B10: Pos | C10: Age@Signing | D10: Transfer Season | E10: Manager | F10: Transfer Type | G10: Fee Paid (€m) | H10: Club Signed From | I10: Source League | J10: Nationality | K10: Current Status | L10: Current Market Value (€m) | M10: Sale Fee (€m) | N10: Valuation Basis | O10: Value Used (€m) | P10: Gain/Loss Type | Q10: Value Gain/Loss (€m) | R10: Return on Fee (%) | S10: MV at Signing (€m) | T10: Palace Usage | U10: Seasons Played | V10: Usage/Season | W10: Usage/Season per €1m | X10: Rating S1 | Y10: Rating S2 | Z10: Rating S3 | AA10: Rating S4 | AB10: Rating S5 | AC10: Rating S6 | AD10: Rating S7 | AE10: Rating S8 | AF10: Average FotMob Rating | AG10: Value Source URL | AH10: Usage Unit | AI10: Season Data Status | AJ10: Season Data Source
A11: Mamadou Sakho | B11: DF | C11: 27 | D11: 2017/18 | F11: Paid | G11: 28.2 | H11: Liverpool | I11: Premier League | J11: France / Senegal | K11: Released / Free | M11: 0 | N11: =IF(A11="","",IF(LEFT(K11,15)="Still at Palace","Current market value","Sale fee")) -> Sale fee | O11: =IF(K11="Sold",M11,IF(OR(K11="Still at Palace",K11="Still at Palace (on loan)"),L11,0)) -> 0 | P11: =IF(Q11>0,"Gain",IF(Q11<0,"Loss","Neutral")) -> Loss | Q11: =O11-G11 -> -28.2 | R11: =IFERROR(Q11/G11,"") -> -1 | S11: 15 | T11: =SUMIFS('FotMob Seasons'!$F$8:$F$136,'FotMob Seasons'!$A$8:$A$136,A11,'FotMob Seasons'!$H$8:$H$136,"Yes") -> 5223 | U11: =COUNTIFS('FotMob Seasons'!$A$8:$A$136,A11,'FotMob Seasons'!$H$8:$H$136,"Yes") -> 4 | V11: =IFERROR(T11/U11,"") -> 1305.75 | W11: =IFERROR(V11/G11,"") -> 46.303191 | X11: 6.74 | Y11: 6.68 | Z11: 6.16 | AA11: 6.28 | AF11: =IFERROR(AVERAGEIFS('FotMob Seasons'!$G$8:$G$136,'FotMob Seasons'!$A$8:$A$136,A11,'FotMob Seasons'!$H$8:$H$136,"Yes"),"") -> 6.465 | AG11: https://www.transfermarkt.com/crystal-palace/alletransfers/verein/873 | AH11: Minutes | AI11: Complete | AJ11: User-provided FotMob
A12: Alexander Sørloth | B12: FW | C12: 22 | D12: 2017/18 | F12: Paid | G12: 16 | H12: Central Jutland | I12: Super League | J12: Norway | K12: Sold | M12: 20 | N12: =IF(A12="","",IF(LEFT(K12,15)="Still at Palace","Current market value","Sale fee")) -> Sale fee | O12: =IF(K12="Sold",M12,IF(OR(K12="Still at Palace",K12="Still at Palace (on loan)"),L12,0)) -> 20 | P12: =IF(Q12>0,"Gain",IF(Q12<0,"Loss","Neutral")) -> Gain | Q12: =O12-G12 -> 4 | R12: =IFERROR(Q12/G12,"") -> 0.25 | S12: 2 | T12: =SUMIFS('FotMob Seasons'!$F$8:$F$136,'FotMob Seasons'!$A$8:$A$136,A12,'FotMob Seasons'!$H$8:$H$136,"Yes") -> 533 | U12: =COUNTIFS('FotMob Seasons'!$A$8:$A$136,A12,'FotMob Seasons'!$H$8:$H$136,"Yes") -> 2 | V12: =IFERROR(T12/U12,"") -> 266.5 | W12: =IFERROR(V12/G12,"") -> 16.65625 | X12: 6.69 | Y12: 6.08 | AF12: =IFERROR(AVERAGEIFS('FotMob Seasons'!$G$8:$G$136,'FotMob Seasons'!$A$8:$A$136,A12,'FotMob Seasons'!$H$8:$H$136,"Yes"),"") -> 6.385 | AG12: https://www.transfermarkt.com/crystal-palace/alletransfers/verein/873 | AH12: Minutes | AI12: Complete | AJ12: User-provided FotMob
A13: Jaïro Riedewald | B13: MD | C13: 20 | D13: 2017/18 | F13: Paid | G13: 9 | H13: Ajax | I13: Eredivisie | J13: Netherlands / Suriname | K13: Released / Free | M13: 0 | N13: =IF(A13="","",IF(LEFT(K13,15)="Still at Palace","Current market value","Sale fee")) -> Sale fee | O13: =IF(K13="Sold",M13,IF(OR(K13="Still at Palace",K13="Still at Palace (on loan)"),L13,0)) -> 0 | P13: =IF(Q13>0,"Gain",IF(Q13<0,"Loss","Neutral")) -> Loss | Q13: =O13-G13 -> -9 | R13: =IFERROR(Q13/G13,"") -> -1 | S13: 5 | T13: =SUMIFS('FotMob Seasons'!$F$8:$F$136,'FotMob Seasons'!$A$8:$A$136,A13,'FotMob Seasons'!$H$8:$H$136,"Yes") -> 3421 | U13: =COUNTIFS('FotMob Seasons'!$A$8:$A$136,A13,'FotMob Seasons'!$H$8:$H$136,"Yes") -> 7 | V13: =IFERROR(T13/U13,"") -> 488.71429 | W13: =IFERROR(V13/G13,"") -> 54.301587 | X13: 6.31 | Y13: 6.33 | Z13: 6.52 | AA13: 6.27 | AB13: 6.6 | AC13: 6.41 | AF13: =IFERROR(AVERAGEIFS('FotMob Seasons'!$G$8:$G$136,'FotMob Seasons'!$A$8:$A$136,A13,'FotMob Seasons'!$H$8:$H$136,"Yes"),"") -> 6.4066667 | AG13: https://www.transfermarkt.com/crystal-palace/rekordabgaenge/verein/873/saison_id/2024 | AH13: Minutes | AI13: Complete | AJ13: User-provided FotMob
A14: Jarosław Jach | B14: DF | C14: 23 | D14: 2017/18 | F14: Paid | G14: 2.75 | H14: Zagłębie Lubin | I14: Ekstraklasa | J14: Poland | K14: Released / Free | M14: 0 | N14: =IF(A14="","",IF(LEFT(K14,15)="Still at Palace","Current market value","Sale fee")) -> Sale fee | O14: =IF(K14="Sold",M14,IF(OR(K14="Still at Palace",K14="Still at Palace (on loan)"),L14,0)) -> 0 | P14: =IF(Q14>0,"Gain",IF(Q14<0,"Loss","Neutral")) -> Loss | Q14: =O14-G14 -> -2.75 | R14: =IFERROR(Q14/G14,"") -> -1 | S14: 2 | T14: =SUMIFS('FotMob Seasons'!$F$8:$F$136,'FotMob Seasons'!$A$8:$A$136,A14,'FotMob Seasons'!$H$8:$H$136,"Yes") -> 0 | U14: =COUNTIFS('FotMob Seasons'!$A$8:$A$136,A14,'FotMob Seasons'!$H$8:$H$136,"Yes") -> 1 | V14: =IFERROR(T14/U14,"") -> 0 | W14: =IFERROR(V14/G14,"") -> 0 | AF14: =IFERROR(AVERAGEIFS('FotMob Seasons'!$G$8:$G$136,'FotMob Seasons'!$A$8:$A$136,A14,'FotMob Seasons'!$H$8:$H$136,"Yes"),"") | AG14: https://www.transfermarkt.com/crystal-palace/alletransfers/verein/873 | AH14: Minutes | AI14: Complete — no Palace PL usage | AJ14: User-provided FotMob
A15: Diego Cavalieri | B15: GK | C15: 35 | D15: 2017/18 | F15: Free transfer | G15: 0 | H15: Without Club | I15: Without Club | J15: Brazil / Italy | K15: Released / Free | M15: 0 | N15: =IF(A15="","",IF(LEFT(K15,15)="Still at Palace","Current market value","Sale fee")) -> Sale fee | O15: =IF(K15="Sold",M15,IF(OR(K15="Still at Palace",K15="Still at Palace (on loan)"),L15,0)) -> 0 | P15: =IF(Q15>0,"Gain",IF(Q15<0,"Loss","Neutral")) -> Neutral | Q15: =O15-G15 -> 0 | R15: =IFERROR(Q15/G15,"") | S15: 1.75 | T15: =SUMIFS('FotMob Seasons'!$F$8:$F$136,'FotMob Seasons'!$A$8:$A$136,A15,'FotMob Seasons'!$H$8:$H$136,"Yes") -> 0 | U15: =COUNTIFS('FotMob Seasons'!$A$8:$A$136,A15,'FotMob Seasons'!$H$8:$H$136,"Yes") -> 1 | V15: =IFERROR(T15/U15,"") -> 0 | W15: =IFERROR(V15/G15,"") | AF15: =IFERROR(AVERAGEIFS('FotMob Seasons'!$G$8:$G$136,'FotMob Seasons'!$A$8:$A$136,A15,'FotMob Seasons'!$H$8:$H$136,"Yes"),"") | AG15: https://www.transfermarkt.com/crystal-palace/alletransfers/verein/873 | AH15: Matches | AI15: Complete — no Palace PL usage | AJ15: User-provided FotMob
A16: Cheikhou Kouyaté | B16: MD | C16: 28 | D16: 2018/19 | F16: Paid | G16: 10.7 | H16: West Ham | I16: Premier League | J16: Senegal / Belgium | K16: Released / Free | M16: 0 | N16: =IF(A16="","",IF(LEFT(K16,15)="Still at Palace","Current market value","Sale fee")) -> Sale fee | O16: =IF(K16="Sold",M16,IF(OR(K16="Still at Palace",K16="Still at Palace (on loan)"),L16,0)) -> 0 | P16: =IF(Q16>0,"Gain",IF(Q16<0,"Loss","Neutral")) -> Loss | Q16: =O16-G16 -> -10.7 | R16: =IFERROR(Q16/G16,"") -> -1 | S16: 12 | T16: =SUMIFS('FotMob Seasons'!$F$8:$F$136,'FotMob Seasons'!$A$8:$A$136,A16,'FotMob Seasons'!$H$8:$H$136,"Yes") -> 9533 | U16: =COUNTIFS('FotMob Seasons'!$A$8:$A$136,A16,'FotMob Seasons'!$H$8:$H$136,"Yes") -> 4 | V16: =IFERROR(T16/U16,"") -> 2383.25 | W16: =IFERROR(V16/G16,"") -> 222.73364 | X16: 6.46 | Y16: 6.58 | Z16: 6.52 | AA16: 6.99 | AF16: =IFERROR(AVERAGEIFS('FotMob Seasons'!$G$8:$G$136,'FotMob Seasons'!$A$8:$A$136,A16,'FotMob Seasons'!$H$8:$H$136,"Yes"),"") -> 6.6375 | AG16: https://www.transfermarkt.com/crystal-palace/alletransfers/verein/873 | AH16: Minutes | AI16: Complete | AJ16: User-provided FotMob
A17: Max Meyer | B17: MD | C17: 22 | D17: 2018/19 | F17: Free transfer | G17: 0 | H17: FC Schalke 04 | I17: Bundesliga | J17: Germany | K17: Released / Free | M17: 0 | N17: =IF(A17="","",IF(LEFT(K17,15)="Still at Palace","Current market value","Sale fee")) -> Sale fee | O17: =IF(K17="Sold",M17,IF(OR(K17="Still at Palace",K17="Still at Palace (on loan)"),L17,0)) -> 0 | P17: =IF(Q17>0,"Gain",IF(Q17<0,"Loss","Neutral")) -> Neutral | Q17: =O17-G17 -> 0 | R17: =IFERROR(Q17/G17,"") | S17: 18 | T17: =SUMIFS('FotMob Seasons'!$F$8:$F$136,'FotMob Seasons'!$A$8:$A$136,A17,'FotMob Seasons'!$H$8:$H$136,"Yes") -> 2060 | U17: =COUNTIFS('FotMob Seasons'!$A$8:$A$136,A17,'FotMob Seasons'!$H$8:$H$136,"Yes") -> 3 | V17: =IFERROR(T17/U17,"") -> 686.66667 | W17: =IFERROR(V17/G17,"") | X17: 6.47 | Y17: 6.02 | AF17: =IFERROR(AVERAGEIFS('FotMob Seasons'!$G$8:$G$136,'FotMob Seasons'!$A$8:$A$136,A17,'FotMob Seasons'!$H$8:$H$136,"Yes"),"") -> 6.245 | AG17: https://www.transfermarkt.com/crystal-palace/alletransfers/verein/873 | AH17: Minutes | AI17: Complete | AJ17: User-provided FotMob
A18: Bakary Sako | B18: FW | C18: 30 | D18: 2018/19 | F18: Free transfer | G18: 0 | H18: West Brom | I18: Championship | J18: Mali / France | K18: Released / Free | M18: 0 | N18: =IF(A18="","",IF(LEFT(K18,15)="Still at Palace","Current market value","Sale fee")) -> Sale fee | O18: =IF(K18="Sold",M18,IF(OR(K18="Still at Palace",K18="Still at Palace (on loan)"),L18,0)) -> 0 | P18: =IF(Q18>0,"Gain",IF(Q18<0,"Loss","Neutral")) -> Neutral | Q18: =O18-G18 -> 0 | R18: =IFERROR(Q18/G18,"") | S18: 5 | T18: =SUMIFS('FotMob Seasons'!$F$8:$F$136,'FotMob Seasons'!$A$8:$A$136,A18,'FotMob Seasons'!$H$8:$H$136,"Yes") -> 26 | U18: =COUNTIFS('FotMob Seasons'!$A$8:$A$136,A18,'FotMob Seasons'!$H$8:$H$136,"Yes") -> 1 | V18: =IFERROR(T18/U18,"") -> 26 | W18: =IFERROR(V18/G18,"") | X18: 5.87 | AF18: =IFERROR(AVERAGEIFS('FotMob Seasons'!$G$8:$G$136,'FotMob Seasons'!$A$8:$A$136,A18,'FotMob Seasons'!$H$8:$H$136,"Yes"),"") -> 5.87 | AG18: https://www.transfermarkt.com/crystal-palace/alletransfers/verein/873 | AH18: Minutes | AI18: Complete | AJ18: User-provided FotMob
A19: Vicente Guaita | B19: GK | C19: 31 | D19: 2018/19 | F19: Free transfer | G19: 0 | H19: Getafe | I19: LaLiga | J19: Spain | K19: Released / Free | M19: 0 | N19: =IF(A19="","",IF(LEFT(K19,15)="Still at Palace","Current market value","Sale fee")) -> Sale fee | O19: =IF(K19="Sold",M19,IF(OR(K19="Still at Palace",K19="Still at Palace (on loan)"),L19,0)) -> 0 | P19: =IF(Q19>0,"Gain",IF(Q19<0,"Loss","Neutral")) -> Neutral | Q19: =O19-G19 -> 0 | R19: =IFERROR(Q19/G19,"") | S19: 5 | T19: =SUMIFS('FotMob Seasons'!$F$8:$F$136,'FotMob Seasons'!$A$8:$A$136,A19,'FotMob Seasons'!$H$8:$H$136,"Yes") -> 149 | U19: =COUNTIFS('FotMob Seasons'!$A$8:$A$136,A19,'FotMob Seasons'!$H$8:$H$136,"Yes") -> 5 | V19: =IFERROR(T19/U19,"") -> 29.8 | W19: =IFERROR(V19/G19,"") | X19: 6.44 | Y19: 6.46 | Z19: 6.13 | AA19: 6.65 | AB19: 6.66 | AF19: =IFERROR(AVERAGEIFS('FotMob Seasons'!$G$8:$G$136,'FotMob Seasons'!$A$8:$A$136,A19,'FotMob Seasons'!$H$8:$H$136,"Yes"),"") -> 6.468 | AG19: https://www.transfermarkt.com/crystal-palace/alletransfers/verein/873 | AH19: Matches | AI19: Complete | AJ19: User-provided FotMob
A20: James McCarthy | B20: MD | C20: 28 | D20: 2019/20 | F20: Paid | G20: 3.3 | H20: Everton | I20: Premier League | J20: Ireland / Scotland | K20: Released / Free | M20: 0 | N20: =IF(A20="","",IF(LEFT(K20,15)="Still at Palace","Current market value","Sale fee")) -> Sale fee | O20: =IF(K20="Sold",M20,IF(OR(K20="Still at Palace",K20="Still at Palace (on loan)"),L20,0)) -> 0 | P20: =IF(Q20>0,"Gain",IF(Q20<0,"Loss","Neutral")) -> Loss | Q20: =O20-G20 -> -3.3 | R20: =IFERROR(Q20/G20,"") -> -1 | S20: 5 | T20: =SUMIFS('FotMob Seasons'!$F$8:$F$136,'FotMob Seasons'!$A$8:$A$136,A20,'FotMob Seasons'!$H$8:$H$136,"Yes") -> 2495 | U20: =COUNTIFS('FotMob Seasons'!$A$8:$A$136,A20,'FotMob Seasons'!$H$8:$H$136,"Yes") -> 2 | V20: =IFERROR(T20/U20,"") -> 1247.5 | W20: =IFERROR(V20/G20,"") -> 378.0303 | X20: 6.42 | Y20: 6.48 | AF20: =IFERROR(AVERAGEIFS('FotMob Seasons'!$G$8:$G$136,'FotMob Seasons'!$A$8:$A$136,A20,'FotMob Seasons'!$H$8:$H$136,"Yes"),"") -> 6.45 | AG20: https://www.transfermarkt.com/crystal-palace/alletransfers/verein/873 | AH20: Minutes | AI20: Complete | AJ20: User-provided FotMob
A21: Jordan Ayew | B21: FW | C21: 27 | D21: 2019/20 | F21: Paid | G21: 2.8 | H21: Swansea City | I21: Championship | J21: Ghana / France | K21: Sold | M21: 5.9 | N21: =IF(A21="","",IF(LEFT(K21,15)="Still at Palace","Current market value","Sale fee")) -> Sale fee | O21: =IF(K21="Sold",M21,IF(OR(K21="Still at Palace",K21="Still at Palace (on loan)"),L21,0)) -> 5.9 | P21: =IF(Q21>0,"Gain",IF(Q21<0,"Loss","Neutral")) -> Gain | Q21: =O21-G21 -> 3.1 | R21: =IFERROR(Q21/G21,"") -> 1.1071429 | S21: 8 | T21: =SUMIFS('FotMob Seasons'!$F$8:$F$136,'FotMob Seasons'!$A$8:$A$136,A21,'FotMob Seasons'!$H$8:$H$136,"Yes") -> 12594 | U21: =COUNTIFS('FotMob Seasons'!$A$8:$A$136,A21,'FotMob Seasons'!$H$8:$H$136,"Yes") -> 5 | V21: =IFERROR(T21/U21,"") -> 2518.8 | W21: =IFERROR(V21/G21,"") -> 899.57143 | X21: 6.48 | Y21: 6.38 | Z21: 6.75 | AA21: 6.84 | AB21: 7 | AF21: =IFERROR(AVERAGEIFS('FotMob Seasons'!$G$8:$G$136,'FotMob Seasons'!$A$8:$A$136,A21,'FotMob Seasons'!$H$8:$H$136,"Yes"),"") -> 6.69 | AG21: https://www.transfermarkt.com/crystal-palace/rekordabgaenge/verein/873/saison_id/2024 | AH21: Minutes | AI21: Complete | AJ21: User-provided FotMob
A22: Gary Cahill | B22: DF | C22: 33 | D22: 2019/20 | F22: Free transfer | G22: 0 | H22: Chelsea | I22: Premier League | J22: England | K22: Released / Free | M22: 0 | N22: =IF(A22="","",IF(LEFT(K22,15)="Still at Palace","Current market value","Sale fee")) -> Sale fee | O22: =IF(K22="Sold",M22,IF(OR(K22="Still at Palace",K22="Still at Palace (on loan)"),L22,0)) -> 0 | P22: =IF(Q22>0,"Gain",IF(Q22<0,"Loss","Neutral")) -> Neutral | Q22: =O22-G22 -> 0 | R22: =IFERROR(Q22/G22,"") | S22: 8 | T22: =SUMIFS('FotMob Seasons'!$F$8:$F$136,'FotMob Seasons'!$A$8:$A$136,A22,'FotMob Seasons'!$H$8:$H$136,"Yes") -> 3968 | U22: =COUNTIFS('FotMob Seasons'!$A$8:$A$136,A22,'FotMob Seasons'!$H$8:$H$136,"Yes") -> 2 | V22: =IFERROR(T22/U22,"") -> 1984 | W22: =IFERROR(V22/G22,"") | X22: 6.54 | Y22: 6.37 | AF22: =IFERROR(AVERAGEIFS('FotMob Seasons'!$G$8:$G$136,'FotMob Seasons'!$A$8:$A$136,A22,'FotMob Seasons'!$H$8:$H$136,"Yes"),"") -> 6.455 | AG22: https://www.transfermarkt.com/crystal-palace/alletransfers/verein/873 | AH22: Minutes | AI22: Complete | AJ22: User-provided FotMob
A23: Stephen Henderson | B23: GK | C23: 31 | D23: 2019/20 | F23: Free transfer | G23: 0 | H23: Nottingham Forest | I23: Championship | J23: Ireland | K23: Released / Free | M23: 0 | N23: =IF(A23="","",IF(LEFT(K23,15)="Still at Palace","Current market value","Sale fee")) -> Sale fee | O23: =IF(K23="Sold",M23,IF(OR(K23="Still at Palace",K23="Still at Palace (on loan)"),L23,0)) -> 0 | P23: =IF(Q23>0,"Gain",IF(Q23<0,"Loss","Neutral")) -> Neutral | Q23: =O23-G23 -> 0 | R23: =IFERROR(Q23/G23,"") | S23: 0.5 | T23: =SUMIFS('FotMob Seasons'!$F$8:$F$136,'FotMob Seasons'!$A$8:$A$136,A23,'FotMob Seasons'!$H$8:$H$136,"Yes") -> 0 | U23: =COUNTIFS('FotMob Seasons'!$A$8:$A$136,A23,'FotMob Seasons'!$H$8:$H$136,"Yes") -> 1 | V23: =IFERROR(T23/U23,"") -> 0 | W23: =IFERROR(V23/G23,"") | AF23: =IFERROR(AVERAGEIFS('FotMob Seasons'!$G$8:$G$136,'FotMob Seasons'!$A$8:$A$136,A23,'FotMob Seasons'!$H$8:$H$136,"Yes"),"") | AG23: https://www.transfermarkt.com/crystal-palace/alletransfers/verein/873 | AH23: Matches | AI23: Complete — no Palace PL usage | AJ23: User-provided FotMob
A24: Eberechi Eze | B24: MD | C24: 22 | D24: 2020/21 | F24: Paid | G24: 17.8 | H24: QPR | I24: Championship | J24: England / Nigeria | K24: Sold | M24: 69.3 | N24: =IF(A24="","",IF(LEFT(K24,15)="Still at Palace","Current market value","Sale fee")) -> Sale fee | O24: =IF(K24="Sold",M24,IF(OR(K24="Still at Palace",K24="Still at Palace (on loan)"),L24,0)) -> 69.3 | P24: =IF(Q24>0,"Gain",IF(Q24<0,"Loss","Neutral")) -> Gain | Q24: =O24-G24 -> 51.5 | R24: =IFERROR(Q24/G24,"") -> 2.8932584 | S24: 9 | T24: =SUMIFS('FotMob Seasons'!$F$8:$F$136,'FotMob Seasons'!$A$8:$A$136,A24,'FotMob Seasons'!$H$8:$H$136,"Yes") -> 10471 | U24: =COUNTIFS('FotMob Seasons'!$A$8:$A$136,A24,'FotMob Seasons'!$H$8:$H$136,"Yes") -> 5 | V24: =IFERROR(T24/U24,"") -> 2094.2 | W24: =IFERROR(V24/G24,"") -> 117.65169 | X24: 6.92 | Y24: 6.85 | Z24: 7.27 | AA24: 7.6 | AB24: 7.4 | AF24: =IFERROR(AVERAGEIFS('FotMob Seasons'!$G$8:$G$136,'FotMob Seasons'!$A$8:$A$136,A24,'FotMob Seasons'!$H$8:$H$136,"Yes"),"") -> 7.208 | AG24: https://www.transfermarkt.com/crystal-palace/rekordabgaenge/verein/873/saison_id/2025/pos//detailpos/0/w_s//plus/1 | AH24: Minutes | AI24: Complete | AJ24: User-provided FotMob
A25: Jack Butland | B25: GK | C25: 27 | D25: 2020/21 | F25: Paid | G25: 1.1 | H25: Stoke City | I25: Championship | J25: England | K25: Released / Free | M25: 0 | N25: =IF(A25="","",IF(LEFT(K25,15)="Still at Palace","Current market value","Sale fee")) -> Sale fee | O25: =IF(K25="Sold",M25,IF(OR(K25="Still at Palace",K25="Still at Palace (on loan)"),L25,0)) -> 0 | P25: =IF(Q25>0,"Gain",IF(Q25<0,"Loss","Neutral")) -> Loss | Q25: =O25-G25 -> -1.1 | R25: =IFERROR(Q25/G25,"") -> -1 | S25: 3.5 | T25: =SUMIFS('FotMob Seasons'!$F$8:$F$136,'FotMob Seasons'!$A$8:$A$136,A25,'FotMob Seasons'!$H$8:$H$136,"Yes") -> 10 | U25: =COUNTIFS('FotMob Seasons'!$A$8:$A$136,A25,'FotMob Seasons'!$H$8:$H$136,"Yes") -> 2 | V25: =IFERROR(T25/U25,"") -> 5 | W25: =IFERROR(V25/G25,"") -> 4.5454545 | X25: 6.38 | Y25: 6.26 | AF25: =IFERROR(AVERAGEIFS('FotMob Seasons'!$G$8:$G$136,'FotMob Seasons'!$A$8:$A$136,A25,'FotMob Seasons'!$H$8:$H$136,"Yes"),"") -> 6.32 | AG25: https://www.transfermarkt.com/crystal-palace/alletransfers/verein/873 | AH25: Matches | AI25: Complete | AJ25: User-provided FotMob
A26: Nathaniel Clyne | B26: DF | C26: 29 | D26: 2020/21 | F26: Free transfer | G26: 0 | H26: Liverpool | I26: Premier League | J26: England / Grenada | K26: Still at Palace | L26: 0.3 | N26: =IF(A26="","",IF(LEFT(K26,15)="Still at Palace","Current market value","Sale fee")) -> Current market value | O26: =IF(K26="Sold",M26,IF(OR(K26="Still at Palace",K26="Still at Palace (on loan)"),L26,0)) -> 0.3 | P26: =IF(Q26>0,"Gain",IF(Q26<0,"Loss","Neutral")) -> Gain | Q26: =O26-G26 -> 0.3 | R26: =IFERROR(Q26/G26,"") | S26: 8 | T26: =SUMIFS('FotMob Seasons'!$F$8:$F$136,'FotMob Seasons'!$A$8:$A$136,A26,'FotMob Seasons'!$H$8:$H$136,"Yes") -> 6554 | U26: =COUNTIFS('FotMob Seasons'!$A$8:$A$136,A26,'FotMob Seasons'!$H$8:$H$136,"Yes") -> 6 | V26: =IFERROR(T26/U26,"") -> 1092.3333 | W26: =IFERROR(V26/G26,"") | X26: 6.37 | Y26: 6.97 | Z26: 6.6 | AA26: 6.82 | AB26: 6.22 | AC26: 6.68 | AF26: =IFERROR(AVERAGEIFS('FotMob Seasons'!$G$8:$G$136,'FotMob Seasons'!$A$8:$A$136,A26,'FotMob Seasons'!$H$8:$H$136,"Yes"),"") -> 6.61 | AG26: https://www.transfermarkt.com/crystal-palace/marktwertanalyse/verein/873 | AH26: Minutes | AI26: Complete | AJ26: User-provided FotMob
A27: Nathan Ferguson | B27: DF | C27: 19 | D27: 2020/21 | F27: Free transfer | G27: 0 | H27: West Brom | I27: Premier League | J27: England / Jamaica | K27: Released / Free | M27: 0 | N27: =IF(A27="","",IF(LEFT(K27,15)="Still at Palace","Current market value","Sale fee")) -> Sale fee | O27: =IF(K27="Sold",M27,IF(OR(K27="Still at Palace",K27="Still at Palace (on loan)"),L27,0)) -> 0 | P27: =IF(Q27>0,"Gain",IF(Q27<0,"Loss","Neutral")) -> Neutral | Q27: =O27-G27 -> 0 | R27: =IFERROR(Q27/G27,"") | S27: 4 | T27: =SUMIFS('FotMob Seasons'!$F$8:$F$136,'FotMob Seasons'!$A$8:$A$136,A27,'FotMob Seasons'!$H$8:$H$136,"Yes") -> 8 | U27: =COUNTIFS('FotMob Seasons'!$A$8:$A$136,A27,'FotMob Seasons'!$H$8:$H$136,"Yes") -> 4 | V27: =IFERROR(T27/U27,"") -> 2 | W27: =IFERROR(V27/G27,"") | AF27: =IFERROR(AVERAGEIFS('FotMob Seasons'!$G$8:$G$136,'FotMob Seasons'!$A$8:$A$136,A27,'FotMob Seasons'!$H$8:$H$136,"Yes"),"") | AG27: https://www.transfermarkt.com/crystal-palace/rekordabgaenge/verein/873/saison_id/2024 | AH27: Minutes | AI27: Complete — some low-use ratings N/A | AJ27: User-provided FotMob
A28: Marc Guéhi | B28: DF | C28: 21 | D28: 2021/22 | F28: Paid | G28: 23.34 | H28: Chelsea | I28: Premier League | J28: England / Côte d’Ivoire | K28: Sold | M28: 23 | N28: =IF(A28="","",IF(LEFT(K28,15)="Still at Palace","Current market value","Sale fee")) -> Sale fee | O28: =IF(K28="Sold",M28,IF(OR(K28="Still at Palace",K28="Still at Palace (on loan)"),L28,0)) -> 23 | P28: =IF(Q28>0,"Gain",IF(Q28<0,"Loss","Neutral")) -> Loss | Q28: =O28-G28 -> -0.34 | R28: =IFERROR(Q28/G28,"") -> -0.014567266 | S28: 10 | T28: =SUMIFS('FotMob Seasons'!$F$8:$F$136,'FotMob Seasons'!$A$8:$A$136,A28,'FotMob Seasons'!$H$8:$H$136,"Yes") -> 11632 | U28: =COUNTIFS('FotMob Seasons'!$A$8:$A$136,A28,'FotMob Seasons'!$H$8:$H$136,"Yes") -> 4 | V28: =IFERROR(T28/U28,"") -> 2908 | W28: =IFERROR(V28/G28,"") -> 124.59297 | X28: 7.04 | Y28: 7.02 | Z28: 6.79 | AA28: 6.92 | AF28: =IFERROR(AVERAGEIFS('FotMob Seasons'!$G$8:$G$136,'FotMob Seasons'!$A$8:$A$136,A28,'FotMob Seasons'!$H$8:$H$136,"Yes"),"") -> 6.9425 | AG28: https://www.transfermarkt.com/crystal-palace/rekordabgaenge/verein/873/saison_id/2025/pos//detailpos/0/w_s//plus/1 | AH28: Minutes | AI28: Complete | AJ28: User-provided FotMob
A29: Joachim Andersen | B29: DF | C29: 25 | D29: 2021/22 | F29: Paid | G29: 17.5 | H29: Lyon | I29: Ligue 1 | J29: Denmark | K29: Sold | M29: 29.5 | N29: =IF(A29="","",IF(LEFT(K29,15)="Still at Palace","Current market value","Sale fee")) -> Sale fee | O29: =IF(K29="Sold",M29,IF(OR(K29="Still at Palace",K29="Still at Palace (on loan)"),L29,0)) -> 29.5 | P29: =IF(Q29>0,"Gain",IF(Q29<0,"Loss","Neutral")) -> Gain | Q29: =O29-G29 -> 12 | R29: =IFERROR(Q29/G29,"") -> 0.68571429 | S29: 22 | T29: =SUMIFS('FotMob Seasons'!$F$8:$F$136,'FotMob Seasons'!$A$8:$A$136,A29,'FotMob Seasons'!$H$8:$H$136,"Yes") -> 9114 | U29: =COUNTIFS('FotMob Seasons'!$A$8:$A$136,A29,'FotMob Seasons'!$H$8:$H$136,"Yes") -> 3 | V29: =IFERROR(T29/U29,"") -> 3038 | W29: =IFERROR(V29/G29,"") -> 173.6 | X29: 6.91 | Y29: 7.06 | Z29: 7.03 | AF29: =IFERROR(AVERAGEIFS('FotMob Seasons'!$G$8:$G$136,'FotMob Seasons'!$A$8:$A$136,A29,'FotMob Seasons'!$H$8:$H$136,"Yes"),"") -> 7 | AG29: https://www.transfermarkt.com/crystal-palace/rekordabgaenge/verein/873/saison_id/2024 | AH29: Minutes | AI29: Complete | AJ29: FotMob via CraftedFC
A30: Odsonne Édouard | B30: FW | C30: 23 | D30: 2021/22 | F30: Paid | G30: 16.3 | H30: Celtic | I30: Premiership | J30: France / Haiti | K30: Sold | M30: 3.7 | N30: =IF(A30="","",IF(LEFT(K30,15)="Still at Palace","Current market value","Sale fee")) -> Sale fee | O30: =IF(K30="Sold",M30,IF(OR(K30="Still at Palace",K30="Still at Palace (on loan)"),L30,0)) -> 3.7 | P30: =IF(Q30>0,"Gain",IF(Q30<0,"Loss","Neutral")) -> Loss | Q30: =O30-G30 -> -12.6 | R30: =IFERROR(Q30/G30,"") -> -0.77300613 | S30: 17 | T30: =SUMIFS('FotMob Seasons'!$F$8:$F$136,'FotMob Seasons'!$A$8:$A$136,A30,'FotMob Seasons'!$H$8:$H$136,"Yes") -> 4924 | U30: =COUNTIFS('FotMob Seasons'!$A$8:$A$136,A30,'FotMob Seasons'!$H$8:$H$136,"Yes") -> 3 | V30: =IFERROR(T30/U30,"") -> 1641.3333 | W30: =IFERROR(V30/G30,"") -> 100.6953 | X30: 6.78 | Y30: 6.43 | Z30: 6.75 | AF30: =IFERROR(AVERAGEIFS('FotMob Seasons'!$G$8:$G$136,'FotMob Seasons'!$A$8:$A$136,A30,'FotMob Seasons'!$H$8:$H$136,"Yes"),"") -> 6.6533333 | AG30: https://www.transfermarkt.com/crystal-palace/rekordabgaenge/verein/873/saison_id/2025/pos//detailpos/0/w_s//plus/1 | AH30: Minutes | AI30: Complete; 1 partial season excluded | AJ30: FotMob via CraftedFC
A31: Jean-Philippe Mateta | B31: FW | C31: 24 | D31: 2021/22 | F31: Paid | G31: 11 | H31: Mainz | I31: Bundesliga | J31: France / DR Congo | K31: Still at Palace | L31: 30 | N31: =IF(A31="","",IF(LEFT(K31,15)="Still at Palace","Current market value","Sale fee")) -> Current market value | O31: =IF(K31="Sold",M31,IF(OR(K31="Still at Palace",K31="Still at Palace (on loan)"),L31,0)) -> 30 | P31: =IF(Q31>0,"Gain",IF(Q31<0,"Loss","Neutral")) -> Gain | Q31: =O31-G31 -> 19 | R31: =IFERROR(Q31/G31,"") -> 1.7272727 | S31: 6 | T31: =SUMIFS('FotMob Seasons'!$F$8:$F$136,'FotMob Seasons'!$A$8:$A$136,A31,'FotMob Seasons'!$H$8:$H$136,"Yes") -> 9061 | U31: =COUNTIFS('FotMob Seasons'!$A$8:$A$136,A31,'FotMob Seasons'!$H$8:$H$136,"Yes") -> 5 | V31: =IFERROR(T31/U31,"") -> 1812.2 | W31: =IFERROR(V31/G31,"") -> 164.74545 | X31: 6.6 | Y31: 6.15 | Z31: 6.95 | AA31: 6.86 | AB31: 6.68 | AF31: =IFERROR(AVERAGEIFS('FotMob Seasons'!$G$8:$G$136,'FotMob Seasons'!$A$8:$A$136,A31,'FotMob Seasons'!$H$8:$H$136,"Yes"),"") -> 6.648 | AG31: https://www.transfermarkt.com/crystal-palace/marktwertanalyse/verein/873 | AH31: Minutes | AI31: Complete | AJ31: FotMob via CraftedFC
A32: Michael Olise | B32: FW | C32: 19 | D32: 2021/22 | F32: Paid | G32: 9.3 | H32: Reading | I32: Championship | J32: France / England | K32: Sold | M32: 53 | N32: =IF(A32="","",IF(LEFT(K32,15)="Still at Palace","Current market value","Sale fee")) -> Sale fee | O32: =IF(K32="Sold",M32,IF(OR(K32="Still at Palace",K32="Still at Palace (on loan)"),L32,0)) -> 53 | P32: =IF(Q32>0,"Gain",IF(Q32<0,"Loss","Neutral")) -> Gain | Q32: =O32-G32 -> 43.7 | R32: =IFERROR(Q32/G32,"") -> 4.6989247 | S32: 15 | T32: =SUMIFS('FotMob Seasons'!$F$8:$F$136,'FotMob Seasons'!$A$8:$A$136,A32,'FotMob Seasons'!$H$8:$H$136,"Yes") -> 5170 | U32: =COUNTIFS('FotMob Seasons'!$A$8:$A$136,A32,'FotMob Seasons'!$H$8:$H$136,"Yes") -> 3 | V32: =IFERROR(T32/U32,"") -> 1723.3333 | W32: =IFERROR(V32/G32,"") -> 185.30466 | X32: 6.95 | Y32: 7.25 | Z32: 7.71 | AF32: =IFERROR(AVERAGEIFS('FotMob Seasons'!$G$8:$G$136,'FotMob Seasons'!$A$8:$A$136,A32,'FotMob Seasons'!$H$8:$H$136,"Yes"),"") -> 7.3033333 | AG32: https://www.transfermarkt.com/crystal-palace/rekordabgaenge/verein/873/saison_id/2024 | AH32: Minutes | AI32: Complete | AJ32: FotMob via CraftedFC
A33: Will Hughes | B33: MD | C33: 26 | D33: 2021/22 | F33: Paid | G33: 7 | H33: Watford | I33: Premier League | J33: England | K33: Still at Palace | L33: 5 | N33: =IF(A33="","",IF(LEFT(K33,15)="Still at Palace","Current market value","Sale fee")) -> Current market value | O33: =IF(K33="Sold",M33,IF(OR(K33="Still at Palace",K33="Still at Palace (on loan)"),L33,0)) -> 5 | P33: =IF(Q33>0,"Gain",IF(Q33<0,"Loss","Neutral")) -> Loss | Q33: =O33-G33 -> -2 | R33: =IFERROR(Q33/G33,"") -> -0.28571429 | S33: 7 | T33: =SUMIFS('FotMob Seasons'!$F$8:$F$136,'FotMob Seasons'!$A$8:$A$136,A33,'FotMob Seasons'!$H$8:$H$136,"Yes") -> 7470 | U33: =COUNTIFS('FotMob Seasons'!$A$8:$A$136,A33,'FotMob Seasons'!$H$8:$H$136,"Yes") -> 5 | V33: =IFERROR(T33/U33,"") -> 1494 | W33: =IFERROR(V33/G33,"") -> 213.42857 | X33: 6.53 | Y33: 6.78 | Z33: 6.72 | AA33: 6.56 | AF33: =IFERROR(AVERAGEIFS('FotMob Seasons'!$G$8:$G$136,'FotMob Seasons'!$A$8:$A$136,A33,'FotMob Seasons'!$H$8:$H$136,"Yes"),"") -> 6.71 | AG33: https://www.transfermarkt.com/crystal-palace/marktwertanalyse/verein/873 | AH33: Minutes | AI33: Complete — some low-use ratings N/A | AJ33: FotMob via CraftedFC
A34: Remi Matthews | B34: GK | C34: 27 | D34: 2021/22 | F34: Free transfer | G34: 0 | H34: Sunderland | I34: League One | J34: England | K34: Still at Palace | L34: 0.2 | N34: =IF(A34="","",IF(LEFT(K34,15)="Still at Palace","Current market value","Sale fee")) -> Current market value | O34: =IF(K34="Sold",M34,IF(OR(K34="Still at Palace",K34="Still at Palace (on loan)"),L34,0)) -> 0.2 | P34: =IF(Q34>0,"Gain",IF(Q34<0,"Loss","Neutral")) -> Gain | Q34: =O34-G34 -> 0.2 | R34: =IFERROR(Q34/G34,"") | S34: 0.3 | T34: =SUMIFS('FotMob Seasons'!$F$8:$F$136,'FotMob Seasons'!$A$8:$A$136,A34,'FotMob Seasons'!$H$8:$H$136,"Yes") -> 1 | U34: =COUNTIFS('FotMob Seasons'!$A$8:$A$136,A34,'FotMob Seasons'!$H$8:$H$136,"Yes") -> 4 | V34: =IFERROR(T34/U34,"") -> 0.25 | W34: =IFERROR(V34/G34,"") | AF34: =IFERROR(AVERAGEIFS('FotMob Seasons'!$G$8:$G$136,'FotMob Seasons'!$A$8:$A$136,A34,'FotMob Seasons'!$H$8:$H$136,"Yes"),"") | AG34: https://www.transfermarkt.com/crystal-palace/marktwertanalyse/verein/873 | AH34: Matches | AI34: Complete — some low-use ratings N/A | AJ34: FotMob / official PL
A35: Cheick Doucouré | B35: MD | C35: 22 | D35: 2022/23 | F35: Paid | G35: 22.6 | H35: Lens | I35: Ligue 1 | J35: Mali | K35: Still at Palace | L35: 10 | N35: =IF(A35="","",IF(LEFT(K35,15)="Still at Palace","Current market value","Sale fee")) -> Current market value | O35: =IF(K35="Sold",M35,IF(OR(K35="Still at Palace",K35="Still at Palace (on loan)"),L35,0)) -> 10 | P35: =IF(Q35>0,"Gain",IF(Q35<0,"Loss","Neutral")) -> Loss | Q35: =O35-G35 -> -12.6 | R35: =IFERROR(Q35/G35,"") -> -0.55752212 | S35: 15 | T35: =SUMIFS('FotMob Seasons'!$F$8:$F$136,'FotMob Seasons'!$A$8:$A$136,A35,'FotMob Seasons'!$H$8:$H$136,"Yes") -> 4211 | U35: =COUNTIFS('FotMob Seasons'!$A$8:$A$136,A35,'FotMob Seasons'!$H$8:$H$136,"Yes") -> 4 | V35: =IFERROR(T35/U35,"") -> 1052.75 | W35: =IFERROR(V35/G35,"") -> 46.581858 | X35: 7.12 | AF35: =IFERROR(AVERAGEIFS('FotMob Seasons'!$G$8:$G$136,'FotMob Seasons'!$A$8:$A$136,A35,'FotMob Seasons'!$H$8:$H$136,"Yes"),"") -> 6.9766667 | AG35: https://www.transfermarkt.com/crystal-palace/marktwertanalyse/verein/873 | AH35: Minutes | AI35: Complete — some low-use ratings N/A | AJ35: FotMob / official usage backup
A36: Chris Richards | B36: DF | C36: 22 | D36: 2022/23 | F36: Paid | G36: 12 | H36: Bayern Munich | I36: Bundesliga | J36: USA | K36: Still at Palace | L36: 28 | N36: =IF(A36="","",IF(LEFT(K36,15)="Still at Palace","Current market value","Sale fee")) -> Current market value | O36: =IF(K36="Sold",M36,IF(OR(K36="Still at Palace",K36="Still at Palace (on loan)"),L36,0)) -> 28 | P36: =IF(Q36>0,"Gain",IF(Q36<0,"Loss","Neutral")) -> Gain | Q36: =O36-G36 -> 16 | R36: =IFERROR(Q36/G36,"") -> 1.3333333 | S36: 7.5 | T36: =SUMIFS('FotMob Seasons'!$F$8:$F$136,'FotMob Seasons'!$A$8:$A$136,A36,'FotMob Seasons'!$H$8:$H$136,"Yes") -> 7284 | U36: =COUNTIFS('FotMob Seasons'!$A$8:$A$136,A36,'FotMob Seasons'!$H$8:$H$136,"Yes") -> 4 | V36: =IFERROR(T36/U36,"") -> 1821 | W36: =IFERROR(V36/G36,"") -> 151.75 | X36: 6.84 | Y36: 6.68 | Z36: 6.87 | AF36: =IFERROR(AVERAGEIFS('FotMob Seasons'!$G$8:$G$136,'FotMob Seasons'!$A$8:$A$136,A36,'FotMob Seasons'!$H$8:$H$136,"Yes"),"") -> 6.7725 | AG36: https://www.transfermarkt.com/crystal-palace/marktwertanalyse/verein/873 | AH36: Minutes | AI36: Complete — some low-use ratings N/A | AJ36: FotMob via CraftedFC
A37: Naouirou Ahamada | B37: MD | C37: 20 | D37: 2022/23 | F37: Paid | G37: 12 | H37: Stuttgart | I37: Bundesliga | J37: France / Comoros | K37: Released / Free | M37: 0 | N37: =IF(A37="","",IF(LEFT(K37,15)="Still at Palace","Current market value","Sale fee")) -> Sale fee | O37: =IF(K37="Sold",M37,IF(OR(K37="Still at Palace",K37="Still at Palace (on loan)"),L37,0)) -> 0 | P37: =IF(Q37>0,"Gain",IF(Q37<0,"Loss","Neutral")) -> Loss | Q37: =O37-G37 -> -12 | R37: =IFERROR(Q37/G37,"") -> -1 | S37: 5.5 | T37: =SUMIFS('FotMob Seasons'!$F$8:$F$136,'FotMob Seasons'!$A$8:$A$136,A37,'FotMob Seasons'!$H$8:$H$136,"Yes") -> 419 | U37: =COUNTIFS('FotMob Seasons'!$A$8:$A$136,A37,'FotMob Seasons'!$H$8:$H$136,"Yes") -> 2 | V37: =IFERROR(T37/U37,"") -> 209.5 | W37: =IFERROR(V37/G37,"") -> 17.458333 | AF37: =IFERROR(AVERAGEIFS('FotMob Seasons'!$G$8:$G$136,'FotMob Seasons'!$A$8:$A$136,A37,'FotMob Seasons'!$H$8:$H$136,"Yes"),"") -> 6.18 | AG37: https://www.transfermarkt.com/crystal-palace/rekordabgaenge/verein/873/saison_id/2025/pos//detailpos/0/w_s//plus/1 | AH37: Minutes | AI37: Complete — some low-use ratings N/A | AJ37: FotMob / official usage backup
A38: Sam Johnstone | B38: GK | C38: 29 | D38: 2022/23 | F38: Free transfer | G38: 0 | H38: West Brom | I38: Championship | J38: England | K38: Sold | M38: 11.9 | N38: =IF(A38="","",IF(LEFT(K38,15)="Still at Palace","Current market value","Sale fee")) -> Sale fee | O38: =IF(K38="Sold",M38,IF(OR(K38="Still at Palace",K38="Still at Palace (on loan)"),L38,0)) -> 11.9 | P38: =IF(Q38>0,"Gain",IF(Q38<0,"Loss","Neutral")) -> Gain | Q38: =O38-G38 -> 11.9 | R38: =IFERROR(Q38/G38,"") | S38: 12 | T38: =SUMIFS('FotMob Seasons'!$F$8:$F$136,'FotMob Seasons'!$A$8:$A$136,A38,'FotMob Seasons'!$H$8:$H$136,"Yes") -> 29 | U38: =COUNTIFS('FotMob Seasons'!$A$8:$A$136,A38,'FotMob Seasons'!$H$8:$H$136,"Yes") -> 2 | V38: =IFERROR(T38/U38,"") -> 14.5 | W38: =IFERROR(V38/G38,"") | X38: 6.56 | AF38: =IFERROR(AVERAGEIFS('FotMob Seasons'!$G$8:$G$136,'FotMob Seasons'!$A$8:$A$136,A38,'FotMob Seasons'!$H$8:$H$136,"Yes"),"") -> 6.56 | AG38: https://www.transfermarkt.com/crystal-palace/rekordabgaenge/verein/873/saison_id/2024 | AH38: Matches | AI38: Complete — some low-use ratings N/A | AJ38: FotMob / official PL
A39: Malcolm Ebiowei | B39: FW | C39: 18 | D39: 2022/23 | F39: Free transfer | G39: 0 | H39: Derby County | I39: League One | J39: England / Netherlands | K39: Sold | M39: 1.15 | N39: =IF(A39="","",IF(LEFT(K39,15)="Still at Palace","Current market value","Sale fee")) -> Sale fee | O39: =IF(K39="Sold",M39,IF(OR(K39="Still at Palace",K39="Still at Palace (on loan)"),L39,0)) -> 1.15 | P39: =IF(Q39>0,"Gain",IF(Q39<0,"Loss","Neutral")) -> Gain | Q39: =O39-G39 -> 1.15 | R39: =IFERROR(Q39/G39,"") | S39: 1 | T39: =SUMIFS('FotMob Seasons'!$F$8:$F$136,'FotMob Seasons'!$A$8:$A$136,A39,'FotMob Seasons'!$H$8:$H$136,"Yes") -> 31 | U39: =COUNTIFS('FotMob Seasons'!$A$8:$A$136,A39,'FotMob Seasons'!$H$8:$H$136,"Yes") -> 1 | V39: =IFERROR(T39/U39,"") -> 31 | W39: =IFERROR(V39/G39,"") | AF39: =IFERROR(AVERAGEIFS('FotMob Seasons'!$G$8:$G$136,'FotMob Seasons'!$A$8:$A$136,A39,'FotMob Seasons'!$H$8:$H$136,"Yes"),"") | AG39: https://www.transfermarkt.com/crystal-palace/rekordabgaenge/verein/873/saison_id/2025/pos//detailpos/0/w_s//plus/1 | AH39: Minutes | AI39: Complete — some low-use ratings N/A | AJ39: FotMob / official usage backup
A40: Adam Wharton | B40: MD | C40: 19 | D40: 2023/24 | F40: Paid | G40: 21.1 | H40: Blackburn Rovers | I40: Championship | J40: England | K40: Still at Palace | L40: 70 | N40: =IF(A40="","",IF(LEFT(K40,15)="Still at Palace","Current market value","Sale fee")) -> Current market value | O40: =IF(K40="Sold",M40,IF(OR(K40="Still at Palace",K40="Still at Palace (on loan)"),L40,0)) -> 70 | P40: =IF(Q40>0,"Gain",IF(Q40<0,"Loss","Neutral")) -> Gain | Q40: =O40-G40 -> 48.9 | R40: =IFERROR(Q40/G40,"") -> 2.3175355 | S40: 10 | T40: =SUMIFS('FotMob Seasons'!$F$8:$F$136,'FotMob Seasons'!$A$8:$A$136,A40,'FotMob Seasons'!$H$8:$H$136,"Yes") -> 5193 | U40: =COUNTIFS('FotMob Seasons'!$A$8:$A$136,A40,'FotMob Seasons'!$H$8:$H$136,"Yes") -> 3 | V40: =IFERROR(T40/U40,"") -> 1731 | W40: =IFERROR(V40/G40,"") -> 82.037915 | X40: 7.01 | AF40: =IFERROR(AVERAGEIFS('FotMob Seasons'!$G$8:$G$136,'FotMob Seasons'!$A$8:$A$136,A40,'FotMob Seasons'!$H$8:$H$136,"Yes"),"") -> 7.06 | AG40: https://www.transfermarkt.com/crystal-palace/marktwertanalyse/verein/873 | AH40: Minutes | AI40: Complete — some low-use ratings N/A | AJ40: FotMob via CraftedFC
A41: Matheus França | B41: MD | C41: 19 | D41: 2023/24 | F41: Paid | G41: 20 | H41: Flamengo | I41: Série A | J41: Brazil | K41: Still at Palace (on loan) | L41: 6 | N41: =IF(A41="","",IF(LEFT(K41,15)="Still at Palace","Current market value","Sale fee")) -> Current market value | O41: =IF(K41="Sold",M41,IF(OR(K41="Still at Palace",K41="Still at Palace (on loan)"),L41,0)) -> 6 | P41: =IF(Q41>0,"Gain",IF(Q41<0,"Loss","Neutral")) -> Loss | Q41: =O41-G41 -> -14 | R41: =IFERROR(Q41/G41,"") -> -0.7 | S41: 9 | T41: =SUMIFS('FotMob Seasons'!$F$8:$F$136,'FotMob Seasons'!$A$8:$A$136,A41,'FotMob Seasons'!$H$8:$H$136,"Yes") -> 276 | U41: =COUNTIFS('FotMob Seasons'!$A$8:$A$136,A41,'FotMob Seasons'!$H$8:$H$136,"Yes") -> 2 | V41: =IFERROR(T41/U41,"") -> 138 | W41: =IFERROR(V41/G41,"") -> 6.9 | AF41: =IFERROR(AVERAGEIFS('FotMob Seasons'!$G$8:$G$136,'FotMob Seasons'!$A$8:$A$136,A41,'FotMob Seasons'!$H$8:$H$136,"Yes"),"") -> 6.34 | AG41: https://www.transfermarkt.com/crystal-palace/marktwertanalyse/verein/873 | AH41: Minutes | AI41: Complete — some low-use ratings N/A | AJ41: FotMob / official usage backup
A42: Dean Henderson | B42: GK | C42: 26 | D42: 2023/24 | F42: Paid | G42: 17.5 | H42: Manchester United | I42: Premier League | J42: England | K42: Still at Palace | L42: 28 | N42: =IF(A42="","",IF(LEFT(K42,15)="Still at Palace","Current market value","Sale fee")) -> Current market value | O42: =IF(K42="Sold",M42,IF(OR(K42="Still at Palace",K42="Still at Palace (on loan)"),L42,0)) -> 28 | P42: =IF(Q42>0,"Gain",IF(Q42<0,"Loss","Neutral")) -> Gain | Q42: =O42-G42 -> 10.5 | R42: =IFERROR(Q42/G42,"") -> 0.6 | S42: 18 | T42: =SUMIFS('FotMob Seasons'!$F$8:$F$136,'FotMob Seasons'!$A$8:$A$136,A42,'FotMob Seasons'!$H$8:$H$136,"Yes") -> 93 | U42: =COUNTIFS('FotMob Seasons'!$A$8:$A$136,A42,'FotMob Seasons'!$H$8:$H$136,"Yes") -> 3 | V42: =IFERROR(T42/U42,"") -> 31 | W42: =IFERROR(V42/G42,"") -> 1.7714286 | X42: 7.03 | Y42: 7.01 | AF42: =IFERROR(AVERAGEIFS('FotMob Seasons'!$G$8:$G$136,'FotMob Seasons'!$A$8:$A$136,A42,'FotMob Seasons'!$H$8:$H$136,"Yes"),"") -> 7.02 | AG42: https://www.transfermarkt.com/crystal-palace/marktwertanalyse/verein/873 | AH42: Matches | AI42: Complete — some low-use ratings N/A | AJ42: FotMob via CraftedFC
A43: Daniel Muñoz | B43: DF | C43: 27 | D43: 2023/24 | F43: Paid | G43: 8 | H43: Genk | I43: Jupiler Pro League | J43: Colombia | K43: Still at Palace | L43: 22 | N43: =IF(A43="","",IF(LEFT(K43,15)="Still at Palace","Current market value","Sale fee")) -> Current market value | O43: =IF(K43="Sold",M43,IF(OR(K43="Still at Palace",K43="Still at Palace (on loan)"),L43,0)) -> 22 | P43: =IF(Q43>0,"Gain",IF(Q43<0,"Loss","Neutral")) -> Gain | Q43: =O43-G43 -> 14 | R43: =IFERROR(Q43/G43,"") -> 1.75 | S43: 10 | T43: =SUMIFS('FotMob Seasons'!$F$8:$F$136,'FotMob Seasons'!$A$8:$A$136,A43,'FotMob Seasons'!$H$8:$H$136,"Yes") -> 7075 | U43: =COUNTIFS('FotMob Seasons'!$A$8:$A$136,A43,'FotMob Seasons'!$H$8:$H$136,"Yes") -> 3 | V43: =IFERROR(T43/U43,"") -> 2358.3333 | W43: =IFERROR(V43/G43,"") -> 294.79167 | X43: 7.38 | Y43: 7.15 | AF43: =IFERROR(AVERAGEIFS('FotMob Seasons'!$G$8:$G$136,'FotMob Seasons'!$A$8:$A$136,A43,'FotMob Seasons'!$H$8:$H$136,"Yes"),"") -> 7.2866667 | AG43: https://www.transfermarkt.com/crystal-palace/marktwertanalyse/verein/873 | AH43: Minutes | AI43: Complete — some low-use ratings N/A | AJ43: FotMob via CraftedFC
A44: Rob Holding | B44: DF | C44: 27 | D44: 2023/24 | F44: Paid | G44: 1.2 | H44: Arsenal | I44: Premier League | J44: England / USA | K44: Released / Free | M44: 0 | N44: =IF(A44="","",IF(LEFT(K44,15)="Still at Palace","Current market value","Sale fee")) -> Sale fee | O44: =IF(K44="Sold",M44,IF(OR(K44="Still at Palace",K44="Still at Palace (on loan)"),L44,0)) -> 0 | P44: =IF(Q44>0,"Gain",IF(Q44<0,"Loss","Neutral")) -> Loss | Q44: =O44-G44 -> -1.2 | R44: =IFERROR(Q44/G44,"") -> -1 | S44: 8 | T44: =SUMIFS('FotMob Seasons'!$F$8:$F$136,'FotMob Seasons'!$A$8:$A$136,A44,'FotMob Seasons'!$H$8:$H$136,"Yes") -> 0 | U44: =COUNTIFS('FotMob Seasons'!$A$8:$A$136,A44,'FotMob Seasons'!$H$8:$H$136,"Yes") -> 1 | V44: =IFERROR(T44/U44,"") -> 0 | W44: =IFERROR(V44/G44,"") -> 0 | AF44: =IFERROR(AVERAGEIFS('FotMob Seasons'!$G$8:$G$136,'FotMob Seasons'!$A$8:$A$136,A44,'FotMob Seasons'!$H$8:$H$136,"Yes"),"") | AG44: https://www.transfermarkt.com/crystal-palace/rekordabgaenge/verein/873/saison_id/2025/pos//detailpos/0/w_s//plus/1 | AH44: Minutes | AI44: Complete — no Palace PL usage | AJ44: FotMob / official PL
A45: Jefferson Lerma | B45: MD | C45: 28 | D45: 2023/24 | F45: Free transfer | G45: 0 | H45: Bournemouth | I45: Premier League | J45: Colombia | K45: Still at Palace | L45: 6 | N45: =IF(A45="","",IF(LEFT(K45,15)="Still at Palace","Current market value","Sale fee")) -> Current market value | O45: =IF(K45="Sold",M45,IF(OR(K45="Still at Palace",K45="Still at Palace (on loan)"),L45,0)) -> 6 | P45: =IF(Q45>0,"Gain",IF(Q45<0,"Loss","Neutral")) -> Gain | Q45: =O45-G45 -> 6 | R45: =IFERROR(Q45/G45,"") | S45: 20 | T45: =SUMIFS('FotMob Seasons'!$F$8:$F$136,'FotMob Seasons'!$A$8:$A$136,A45,'FotMob Seasons'!$H$8:$H$136,"Yes") -> 6403 | U45: =COUNTIFS('FotMob Seasons'!$A$8:$A$136,A45,'FotMob Seasons'!$H$8:$H$136,"Yes") -> 3 | V45: =IFERROR(T45/U45,"") -> 2134.3333 | W45: =IFERROR(V45/G45,"") | X45: 7.15 | Y45: 6.77 | Z45: 6.73 | AF45: =IFERROR(AVERAGEIFS('FotMob Seasons'!$G$8:$G$136,'FotMob Seasons'!$A$8:$A$136,A45,'FotMob Seasons'!$H$8:$H$136,"Yes"),"") -> 6.8833333 | AG45: https://www.transfermarkt.com/crystal-palace/marktwertanalyse/verein/873 | AH45: Minutes | AI45: Complete | AJ45: FotMob via CraftedFC
A46: Eddie Nketiah | B46: FW | C46: 25 | D46: 2024/25 | F46: Paid | G46: 29.7 | H46: Arsenal | I46: Premier League | J46: England / Ghana | K46: Still at Palace | L46: 10 | N46: =IF(A46="","",IF(LEFT(K46,15)="Still at Palace","Current market value","Sale fee")) -> Current market value | O46: =IF(K46="Sold",M46,IF(OR(K46="Still at Palace",K46="Still at Palace (on loan)"),L46,0)) -> 10 | P46: =IF(Q46>0,"Gain",IF(Q46<0,"Loss","Neutral")) -> Loss | Q46: =O46-G46 -> -19.7 | R46: =IFERROR(Q46/G46,"") -> -0.66329966 | S46: 30 | T46: =SUMIFS('FotMob Seasons'!$F$8:$F$136,'FotMob Seasons'!$A$8:$A$136,A46,'FotMob Seasons'!$H$8:$H$136,"Yes") -> 1442 | U46: =COUNTIFS('FotMob Seasons'!$A$8:$A$136,A46,'FotMob Seasons'!$H$8:$H$136,"Yes") -> 2 | V46: =IFERROR(T46/U46,"") -> 721 | W46: =IFERROR(V46/G46,"") -> 24.276094 | X46: 6.45 | AF46: =IFERROR(AVERAGEIFS('FotMob Seasons'!$G$8:$G$136,'FotMob Seasons'!$A$8:$A$136,A46,'FotMob Seasons'!$H$8:$H$136,"Yes"),"") -> 6.45 | AG46: https://www.transfermarkt.com/crystal-palace/marktwertanalyse/verein/873 | AH46: Minutes | AI46: Complete — some low-use ratings N/A | AJ46: FotMob via CraftedFC
A47: Maxence Lacroix | B47: DF | C47: 24 | D47: 2024/25 | F47: Paid | G47: 18 | H47: Wolfsburg | I47: Bundesliga | J47: France | K47: Still at Palace | L47: 50 | N47: =IF(A47="","",IF(LEFT(K47,15)="Still at Palace","Current market value","Sale fee")) -> Current market value | O47: =IF(K47="Sold",M47,IF(OR(K47="Still at Palace",K47="Still at Palace (on loan)"),L47,0)) -> 50 | P47: =IF(Q47>0,"Gain",IF(Q47<0,"Loss","Neutral")) -> Gain | Q47: =O47-G47 -> 32 | R47: =IFERROR(Q47/G47,"") -> 1.7777778 | S47: 20 | T47: =SUMIFS('FotMob Seasons'!$F$8:$F$136,'FotMob Seasons'!$A$8:$A$136,A47,'FotMob Seasons'!$H$8:$H$136,"Yes") -> 6205 | U47: =COUNTIFS('FotMob Seasons'!$A$8:$A$136,A47,'FotMob Seasons'!$H$8:$H$136,"Yes") -> 2 | V47: =IFERROR(T47/U47,"") -> 3102.5 | W47: =IFERROR(V47/G47,"") -> 172.36111 | X47: 6.98 | Y47: 7.04 | AF47: =IFERROR(AVERAGEIFS('FotMob Seasons'!$G$8:$G$136,'FotMob Seasons'!$A$8:$A$136,A47,'FotMob Seasons'!$H$8:$H$136,"Yes"),"") -> 7.01 | AG47: https://www.transfermarkt.com/crystal-palace/marktwertanalyse/verein/873 | AH47: Minutes | AI47: Complete | AJ47: FotMob via CraftedFC
A48: Ismaïla Sarr | B48: FW | C48: 26 | D48: 2024/25 | F48: Paid | G48: 15 | H48: Marseille | I48: Ligue 1 | J48: Senegal | K48: Still at Palace | L48: 45 | N48: =IF(A48="","",IF(LEFT(K48,15)="Still at Palace","Current market value","Sale fee")) -> Current market value | O48: =IF(K48="Sold",M48,IF(OR(K48="Still at Palace",K48="Still at Palace (on loan)"),L48,0)) -> 45 | P48: =IF(Q48>0,"Gain",IF(Q48<0,"Loss","Neutral")) -> Gain | Q48: =O48-G48 -> 30 | R48: =IFERROR(Q48/G48,"") -> 2 | S48: 18 | T48: =SUMIFS('FotMob Seasons'!$F$8:$F$136,'FotMob Seasons'!$A$8:$A$136,A48,'FotMob Seasons'!$H$8:$H$136,"Yes") -> 4890 | U48: =COUNTIFS('FotMob Seasons'!$A$8:$A$136,A48,'FotMob Seasons'!$H$8:$H$136,"Yes") -> 2 | V48: =IFERROR(T48/U48,"") -> 2445 | W48: =IFERROR(V48/G48,"") -> 163 | X48: 7.07 | Y48: 6.91 | AF48: =IFERROR(AVERAGEIFS('FotMob Seasons'!$G$8:$G$136,'FotMob Seasons'!$A$8:$A$136,A48,'FotMob Seasons'!$H$8:$H$136,"Yes"),"") -> 6.99 | AG48: https://www.transfermarkt.com/crystal-palace/marktwertanalyse/verein/873 | AH48: Minutes | AI48: Complete | AJ48: FotMob via CraftedFC
A49: Chadi Riad | B49: DF | C49: 21 | D49: 2024/25 | F49: Paid | G49: 15 | H49: Real Betis | I49: LaLiga | J49: Morocco / Spain | K49: Still at Palace | L49: 20 | N49: =IF(A49="","",IF(LEFT(K49,15)="Still at Palace","Current market value","Sale fee")) -> Current market value | O49: =IF(K49="Sold",M49,IF(OR(K49="Still at Palace",K49="Still at Palace (on loan)"),L49,0)) -> 20 | P49: =IF(Q49>0,"Gain",IF(Q49<0,"Loss","Neutral")) -> Gain | Q49: =O49-G49 -> 5 | R49: =IFERROR(Q49/G49,"") -> 0.33333333 | S49: 15 | T49: =SUMIFS('FotMob Seasons'!$F$8:$F$136,'FotMob Seasons'!$A$8:$A$136,A49,'FotMob Seasons'!$H$8:$H$136,"Yes") -> 644 | U49: =COUNTIFS('FotMob Seasons'!$A$8:$A$136,A49,'FotMob Seasons'!$H$8:$H$136,"Yes") -> 2 | V49: =IFERROR(T49/U49,"") -> 322 | W49: =IFERROR(V49/G49,"") -> 21.466667 | AF49: =IFERROR(AVERAGEIFS('FotMob Seasons'!$G$8:$G$136,'FotMob Seasons'!$A$8:$A$136,A49,'FotMob Seasons'!$H$8:$H$136,"Yes"),"") -> 6.7 | AG49: https://www.transfermarkt.com/crystal-palace/marktwertanalyse/verein/873 | AH49: Minutes | AI49: Complete — some low-use ratings N/A | AJ49: FotMob via CraftedFC
A50: Romain Esse | B50: FW | C50: 19 | D50: 2024/25 | F50: Paid | G50: 14.2 | H50: Millwall | I50: Championship | J50: England / Côte d’Ivoire | K50: Still at Palace (on loan) | L50: 10 | N50: =IF(A50="","",IF(LEFT(K50,15)="Still at Palace","Current market value","Sale fee")) -> Current market value | O50: =IF(K50="Sold",M50,IF(OR(K50="Still at Palace",K50="Still at Palace (on loan)"),L50,0)) -> 10 | P50: =IF(Q50>0,"Gain",IF(Q50<0,"Loss","Neutral")) -> Loss | Q50: =O50-G50 -> -4.2 | R50: =IFERROR(Q50/G50,"") -> -0.29577465 | S50: 5 | T50: =SUMIFS('FotMob Seasons'!$F$8:$F$136,'FotMob Seasons'!$A$8:$A$136,A50,'FotMob Seasons'!$H$8:$H$136,"Yes") -> 135 | U50: =COUNTIFS('FotMob Seasons'!$A$8:$A$136,A50,'FotMob Seasons'!$H$8:$H$136,"Yes") -> 1 | V50: =IFERROR(T50/U50,"") -> 135 | W50: =IFERROR(V50/G50,"") -> 9.5070423 | AF50: =IFERROR(AVERAGEIFS('FotMob Seasons'!$G$8:$G$136,'FotMob Seasons'!$A$8:$A$136,A50,'FotMob Seasons'!$H$8:$H$136,"Yes"),"") -> 6.58 | AG50: https://www.transfermarkt.com/crystal-palace/marktwertanalyse/verein/873 | AH50: Minutes | AI50: Complete — some low-use ratings N/A; 1 partial season excluded | AJ50: FotMob via CraftedFC
A51: Daichi Kamada | B51: MD | C51: 27 | D51: 2024/25 | F51: Free transfer | G51: 0 | H51: Lazio | I51: Serie A | J51: Japan | K51: Released / Free | M51: 0 | N51: =IF(A51="","",IF(LEFT(K51,15)="Still at Palace","Current market value","Sale fee")) -> Sale fee | O51: =IF(K51="Sold",M51,IF(OR(K51="Still at Palace",K51="Still at Palace (on loan)"),L51,0)) -> 0 | P51: =IF(Q51>0,"Gain",IF(Q51<0,"Loss","Neutral")) -> Neutral | Q51: =O51-G51 -> 0 | R51: =IFERROR(Q51/G51,"") | S51: 18 | T51: =SUMIFS('FotMob Seasons'!$F$8:$F$136,'FotMob Seasons'!$A$8:$A$136,A51,'FotMob Seasons'!$H$8:$H$136,"Yes") -> 3462 | U51: =COUNTIFS('FotMob Seasons'!$A$8:$A$136,A51,'FotMob Seasons'!$H$8:$H$136,"Yes") -> 2 | V51: =IFERROR(T51/U51,"") -> 1731 | W51: =IFERROR(V51/G51,"") | X51: 6.55 | Y51: 6.84 | AF51: =IFERROR(AVERAGEIFS('FotMob Seasons'!$G$8:$G$136,'FotMob Seasons'!$A$8:$A$136,A51,'FotMob Seasons'!$H$8:$H$136,"Yes"),"") -> 6.695 | AG51: https://www.transfermarkt.com/crystal-palace/alletransfers/verein/873 | AH51: Minutes | AI51: Complete | AJ51: FotMob via CraftedFC
A52: Jørgen Strand Larsen | B52: FW | C52: 25 | D52: 2025/26 | F52: Paid | G52: 49.7 | H52: Wolves | I52: Premier League | J52: Norway | K52: Still at Palace | L52: 40 | N52: =IF(A52="","",IF(LEFT(K52,15)="Still at Palace","Current market value","Sale fee")) -> Current market value | O52: =IF(K52="Sold",M52,IF(OR(K52="Still at Palace",K52="Still at Palace (on loan)"),L52,0)) -> 40 | P52: =IF(Q52>0,"Gain",IF(Q52<0,"Loss","Neutral")) -> Loss | Q52: =O52-G52 -> -9.7 | R52: =IFERROR(Q52/G52,"") -> -0.19517103 | S52: 40 | T52: =SUMIFS('FotMob Seasons'!$F$8:$F$136,'FotMob Seasons'!$A$8:$A$136,A52,'FotMob Seasons'!$H$8:$H$136,"Yes") -> 2316 | U52: =COUNTIFS('FotMob Seasons'!$A$8:$A$136,A52,'FotMob Seasons'!$H$8:$H$136,"Yes") -> 1 | V52: =IFERROR(T52/U52,"") -> 2316 | W52: =IFERROR(V52/G52,"") -> 46.599598 | X52: 6.23 | AF52: =IFERROR(AVERAGEIFS('FotMob Seasons'!$G$8:$G$136,'FotMob Seasons'!$A$8:$A$136,A52,'FotMob Seasons'!$H$8:$H$136,"Yes"),"") -> 6.23 | AG52: https://www.transfermarkt.com/crystal-palace/marktwertanalyse/verein/873 | AH52: Minutes | AI52: Complete | AJ52: FotMob via CraftedFC
A53: Brennan Johnson | B53: FW | C53: 24 | D53: 2025/26 | F53: Paid | G53: 40 | H53: Tottenham | I53: Premier League | J53: Wales / England | K53: Still at Palace | L53: 30 | N53: =IF(A53="","",IF(LEFT(K53,15)="Still at Palace","Current market value","Sale fee")) -> Current market value | O53: =IF(K53="Sold",M53,IF(OR(K53="Still at Palace",K53="Still at Palace (on loan)"),L53,0)) -> 30 | P53: =IF(Q53>0,"Gain",IF(Q53<0,"Loss","Neutral")) -> Loss | Q53: =O53-G53 -> -10 | R53: =IFERROR(Q53/G53,"") -> -0.25 | S53: 35 | T53: =SUMIFS('FotMob Seasons'!$F$8:$F$136,'FotMob Seasons'!$A$8:$A$136,A53,'FotMob Seasons'!$H$8:$H$136,"Yes") -> 1722 | U53: =COUNTIFS('FotMob Seasons'!$A$8:$A$136,A53,'FotMob Seasons'!$H$8:$H$136,"Yes") -> 1 | V53: =IFERROR(T53/U53,"") -> 1722 | W53: =IFERROR(V53/G53,"") -> 43.05 | X53: 6.57 | AF53: =IFERROR(AVERAGEIFS('FotMob Seasons'!$G$8:$G$136,'FotMob Seasons'!$A$8:$A$136,A53,'FotMob Seasons'!$H$8:$H$136,"Yes"),"") -> 6.57 | AG53: https://www.transfermarkt.com/crystal-palace/marktwertanalyse/verein/873 | AH53: Minutes | AI53: Complete | AJ53: FotMob via CraftedFC
A54: Yéremy Pino | B54: FW | C54: 22 | D54: 2025/26 | F54: Paid | G54: 30 | H54: Villarreal | I54: LaLiga | J54: Spain | K54: Still at Palace | L54: 30 | N54: =IF(A54="","",IF(LEFT(K54,15)="Still at Palace","Current market value","Sale fee")) -> Current market value | O54: =IF(K54="Sold",M54,IF(OR(K54="Still at Palace",K54="Still at Palace (on loan)"),L54,0)) -> 30 | P54: =IF(Q54>0,"Gain",IF(Q54<0,"Loss","Neutral")) -> Neutral | Q54: =O54-G54 -> 0 | R54: =IFERROR(Q54/G54,"") -> 0 | S54: 30 | T54: =SUMIFS('FotMob Seasons'!$F$8:$F$136,'FotMob Seasons'!$A$8:$A$136,A54,'FotMob Seasons'!$H$8:$H$136,"Yes") -> 2091 | U54: =COUNTIFS('FotMob Seasons'!$A$8:$A$136,A54,'FotMob Seasons'!$H$8:$H$136,"Yes") -> 1 | V54: =IFERROR(T54/U54,"") -> 2091 | W54: =IFERROR(V54/G54,"") -> 69.7 | X54: 6.71 | AF54: =IFERROR(AVERAGEIFS('FotMob Seasons'!$G$8:$G$136,'FotMob Seasons'!$A$8:$A$136,A54,'FotMob Seasons'!$H$8:$H$136,"Yes"),"") -> 6.71 | AG54: https://www.transfermarkt.com/crystal-palace/marktwertanalyse/verein/873 | AH54: Minutes | AI54: Complete | AJ54: FotMob via CraftedFC
A55: Jaydee Canvot | B55: DF | C55: 19 | D55: 2025/26 | F55: Paid | G55: 25 | H55: Toulouse | I55: Ligue 1 | J55: France / Senegal | K55: Still at Palace | L55: 28 | N55: =IF(A55="","",IF(LEFT(K55,15)="Still at Palace","Current market value","Sale fee")) -> Current market value | O55: =IF(K55="Sold",M55,IF(OR(K55="Still at Palace",K55="Still at Palace (on loan)"),L55,0)) -> 28 | P55: =IF(Q55>0,"Gain",IF(Q55<0,"Loss","Neutral")) -> Gain | Q55: =O55-G55 -> 3 | R55: =IFERROR(Q55/G55,"") -> 0.12 | S55: 4 | T55: =SUMIFS('FotMob Seasons'!$F$8:$F$136,'FotMob Seasons'!$A$8:$A$136,A55,'FotMob Seasons'!$H$8:$H$136,"Yes") -> 1334 | U55: =COUNTIFS('FotMob Seasons'!$A$8:$A$136,A55,'FotMob Seasons'!$H$8:$H$136,"Yes") -> 1 | V55: =IFERROR(T55/U55,"") -> 1334 | W55: =IFERROR(V55/G55,"") -> 53.36 | AF55: =IFERROR(AVERAGEIFS('FotMob Seasons'!$G$8:$G$136,'FotMob Seasons'!$A$8:$A$136,A55,'FotMob Seasons'!$H$8:$H$136,"Yes"),"") -> 6.84 | AG55: https://www.transfermarkt.com/crystal-palace/marktwertanalyse/verein/873 | AH55: Minutes | AI55: Complete — some low-use ratings N/A | AJ55: FotMob via CraftedFC
A56: Borna Sosa | B56: DF | C56: 27 | D56: 2025/26 | F56: Paid | G56: 2.5 | H56: Ajax | I56: Eredivisie | J56: Croatia / Germany | K56: Still at Palace | L56: 3 | N56: =IF(A56="","",IF(LEFT(K56,15)="Still at Palace","Current market value","Sale fee")) -> Current market value | O56: =IF(K56="Sold",M56,IF(OR(K56="Still at Palace",K56="Still at Palace (on loan)"),L56,0)) -> 3 | P56: =IF(Q56>0,"Gain",IF(Q56<0,"Loss","Neutral")) -> Gain | Q56: =O56-G56 -> 0.5 | R56: =IFERROR(Q56/G56,"") -> 0.2 | S56: 4.5 | T56: =SUMIFS('FotMob Seasons'!$F$8:$F$136,'FotMob Seasons'!$A$8:$A$136,A56,'FotMob Seasons'!$H$8:$H$136,"Yes") -> 99 | U56: =COUNTIFS('FotMob Seasons'!$A$8:$A$136,A56,'FotMob Seasons'!$H$8:$H$136,"Yes") -> 1 | V56: =IFERROR(T56/U56,"") -> 99 | W56: =IFERROR(V56/G56,"") -> 39.6 | AF56: =IFERROR(AVERAGEIFS('FotMob Seasons'!$G$8:$G$136,'FotMob Seasons'!$A$8:$A$136,A56,'FotMob Seasons'!$H$8:$H$136,"Yes"),"") | AG56: https://www.transfermarkt.com/crystal-palace/marktwertanalyse/verein/873 | AH56: Minutes | AI56: Complete — some low-use ratings N/A | AJ56: FotMob via CraftedFC
A57: Walter Benítez | B57: GK | C57: 32 | D57: 2025/26 | F57: Free transfer | G57: 0 | H57: PSV | I57: Eredivisie | J57: Argentina / France | K57: Still at Palace | L57: 4 | N57: =IF(A57="","",IF(LEFT(K57,15)="Still at Palace","Current market value","Sale fee")) -> Current market value | O57: =IF(K57="Sold",M57,IF(OR(K57="Still at Palace",K57="Still at Palace (on loan)"),L57,0)) -> 4 | P57: =IF(Q57>0,"Gain",IF(Q57<0,"Loss","Neutral")) -> Gain | Q57: =O57-G57 -> 4 | R57: =IFERROR(Q57/G57,"") | S57: 7.5 | T57: =SUMIFS('FotMob Seasons'!$F$8:$F$136,'FotMob Seasons'!$A$8:$A$136,A57,'FotMob Seasons'!$H$8:$H$136,"Yes") -> 1 | U57: =COUNTIFS('FotMob Seasons'!$A$8:$A$136,A57,'FotMob Seasons'!$H$8:$H$136,"Yes") -> 1 | V57: =IFERROR(T57/U57,"") -> 1 | W57: =IFERROR(V57/G57,"") | AF57: =IFERROR(AVERAGEIFS('FotMob Seasons'!$G$8:$G$136,'FotMob Seasons'!$A$8:$A$136,A57,'FotMob Seasons'!$H$8:$H$136,"Yes"),"") | AG57: https://www.transfermarkt.com/crystal-palace/marktwertanalyse/verein/873 | AH57: Matches | AI57: Complete — some low-use ratings N/A | AJ57: FotMob via CraftedFC
N58: =IF(A58="","",IF(LEFT(K58,15)="Still at Palace","Current market value","Sale fee")) | O58: =IF(A58="","",IF(N58="Current market value",L58,M58)) | P58: =IF(A58="","",IF(N58="Current market value","Unrealised","Realised")) | Q58: =IF(A58="","",IF(AND(ISNUMBER(G58),ISNUMBER(O58)),O58-G58,"")) | R58: =IF(A58="","",IF(AND(ISNUMBER(G58),G58>0,ISNUMBER(Q58)),Q58/G58,"")) | V58: =IF(A58="","",IF(AND(ISNUMBER(T58),ISNUMBER(U58),U58>0),T58/U58,"")) | W58: =IF(A58="","",IF(AND(ISNUMBER(V58),ISNUMBER(G58),G58>0),V58/G58,"")) | AF58: =IF(A58="","",IF(COUNT(X58:AE58)=0,"",AVERAGE(X58:AE58)))
N59: =IF(A59="","",IF(LEFT(K59,15)="Still at Palace","Current market value","Sale fee")) | O59: =IF(A59="","",IF(N59="Current market value",L59,M59)) | P59: =IF(A59="","",IF(N59="Current market value","Unrealised","Realised")) | Q59: =IF(A59="","",IF(AND(ISNUMBER(G59),ISNUMBER(O59)),O59-G59,"")) | R59: =IF(A59="","",IF(AND(ISNUMBER(G59),G59>0,ISNUMBER(Q59)),Q59/G59,"")) | V59: =IF(A59="","",IF(AND(ISNUMBER(T59),ISNUMBER(U59),U59>0),T59/U59,"")) | W59: =IF(A59="","",IF(AND(ISNUMBER(V59),ISNUMBER(G59),G59>0),V59/G59,"")) | AF59: =IF(A59="","",IF(COUNT(X59:AE59)=0,"",AVERAGE(X59:AE59)))
N60: =IF(A60="","",IF(LEFT(K60,15)="Still at Palace","Current market value","Sale fee")) | O60: =IF(A60="","",IF(N60="Current market value",L60,M60)) | P60: =IF(A60="","",IF(N60="Current market value","Unrealised","Realised")) | Q60: =IF(A60="","",IF(AND(ISNUMBER(G60),ISNUMBER(O60)),O60-G60,"")) | R60: =IF(A60="","",IF(AND(ISNUMBER(G60),G60>0,ISNUMBER(Q60)),Q60/G60,"")) | V60: =IF(A60="","",IF(AND(ISNUMBER(T60),ISNUMBER(U60),U60>0),T60/U60,"")) | W60: =IF(A60="","",IF(AND(ISNUMBER(V60),ISNUMBER(G60),G60>0),V60/G60,"")) | AF60: =IF(A60="","",IF(COUNT(X60:AE60)=0,"",AVERAGE(X60:AE60)))

Sheet Method & Sources
A1: VALUATION METHOD AND SOURCES
A3: Item | B3: Method | C3: Formula | D3: Source | E3: Currency | F3: Interpretation | G3: Key limitation | H3: Checked
A4: Still Palace-owned players | B4: Use latest Transfermarkt current market value | C4: Value Used = Current Market Value | D4: https://www.transfermarkt.com/crystal-palace/kader/verein/873 | E4: EUR millions | F4: Unrealised value estimate | G4: Market value is an estimate, not a guaranteed sale price. | H4: 29-Jul-2026
A5: Sold players | B5: Use Transfermarkt-listed departure fee | C5: Value Used = Sale Fee | D5: https://www.transfermarkt.com/crystal-palace/alletransfers/verein/873 | E5: EUR millions | F5: Realised transfer value | G5: Listed fees may omit or simplify add-ons, sell-on clauses or shared proceeds. | H5: 29-Jul-2026
A6: Released / free departures | B6: Record sale fee as zero | C6: Value Used = €0m | D6: https://www.transfermarkt.com/crystal-palace/alletransfers/verein/873 | E6: EUR millions | F6: Realised transfer value | G6: Does not include saved wages or termination costs. | H6: 29-Jul-2026
A7: Value Gain/Loss | B7: Compare a consistent EUR value with the original EUR fee | C7: Value Used − Fee Paid | D7: Workbook formula | E7: EUR millions | F7: Positive = gain; negative = loss | G7: Excludes wages, bonuses, agent fees, add-ons, amortisation and financing. | H7: Automatic
A8: Return on Fee | B8: Scale gain/loss by the original fee | C8: Value Gain/Loss ÷ Fee Paid | D8: Workbook formula | E8: Percentage | F8: Relative transfer-value return | G8: Blank for free transfers because division by zero is not meaningful. | H8: Automatic
A11: IMPORTANT DATA NOTE
A12: The previous workbook mixed pound-denominated labels with euro-denominated Transfermarkt data. This version standardises the original fees, current market values and sale fees to euros, so the gain/loss formulas compare like with like. For players still owned by Palace, the result is unrealised; for departed players, it is realised. Transfermarkt values and reported fees should be treated as consistent research estimates rather than audited accounting figures.

Sheet FotMob Seasons
A1: CRYSTAL PALACE — FOTMOB PREMIER LEAGUE SEASON DATA
A3: PLAYERS | C3: SEASON ROWS | E3: RATED SEASONS | G3: COUNTED SEASONS | I3: EXCLUDED PARTIALS
A4: =COUNTA('Research Tracker'!A11:A57) -> 47 | C4: =COUNTA(A8:A136) -> 129 | E4: =COUNT(G8:G136) -> 103 | G4: =COUNTIFS(H8:H136,"Yes",F8:F136,">0") -> 114 | I4: =COUNTIF(H8:H136,"No") -> 2
A6: Method: Premier League only. Outfield usage is minutes; goalkeeper usage is matches. A season counts only when usage is above zero and Include in Metrics = Yes. The average rating is an unweighted mean of the available FotMob season averages. Zero-minute seasons and ratings not published by FotMob remain blank. Tiny partial departure seasons are excluded where agreed.
A7: Player | B7: Pos | C7: Permanent Transfer Season | D7: Palace Season | E7: Usage Unit | F7: Usage | G7: FotMob Rating | H7: Include in Metrics | I7: Counts as Season | J7: Data Origin | K7: Source URL | L7: Notes
A8: Mamadou Sakho | B8: DF | C8: 2017/18 | D8: 2017/18 | E8: Minutes | F8: 1600 | G8: 6.74 | H8: Yes | I8: =IF(AND(H8="Yes",F8>0),"Yes","No") -> Yes | J8: User-provided FotMob | K8: https://www.fotmob.com/teams/9826/overview/crystal-palace
A9: Mamadou Sakho | B9: DF | C9: 2017/18 | D9: 2018/19 | E9: Minutes | F9: 2417 | G9: 6.68 | H9: Yes | I9: =IF(AND(H9="Yes",F9>0),"Yes","No") -> Yes | J9: User-provided FotMob | K9: https://www.fotmob.com/teams/9826/overview/crystal-palace
A10: Mamadou Sakho | B10: DF | C10: 2017/18 | D10: 2019/20 | E10: Minutes | F10: 931 | G10: 6.16 | H10: Yes | I10: =IF(AND(H10="Yes",F10>0),"Yes","No") -> Yes | J10: User-provided FotMob | K10: https://www.fotmob.com/teams/9826/overview/crystal-palace
A11: Mamadou Sakho | B11: DF | C11: 2017/18 | D11: 2020/21 | E11: Minutes | F11: 275 | G11: 6.28 | H11: Yes | I11: =IF(AND(H11="Yes",F11>0),"Yes","No") -> Yes | J11: User-provided FotMob | K11: https://www.fotmob.com/teams/9826/overview/crystal-palace
A12: Alexander Sørloth | B12: FW | C12: 2017/18 | D12: 2017/18 | E12: Minutes | F12: 360 | G12: 6.69 | H12: Yes | I12: =IF(AND(H12="Yes",F12>0),"Yes","No") -> Yes | J12: User-provided FotMob | K12: https://www.fotmob.com/teams/9826/overview/crystal-palace
A13: Alexander Sørloth | B13: FW | C13: 2017/18 | D13: 2018/19 | E13: Minutes | F13: 173 | G13: 6.08 | H13: Yes | I13: =IF(AND(H13="Yes",F13>0),"Yes","No") -> Yes | J13: User-provided FotMob | K13: https://www.fotmob.com/teams/9826/overview/crystal-palace
A14: Jaïro Riedewald | B14: MD | C14: 2017/18 | D14: 2017/18 | E14: Minutes | F14: 435 | G14: 6.31 | H14: Yes | I14: =IF(AND(H14="Yes",F14>0),"Yes","No") -> Yes | J14: User-provided FotMob | K14: https://www.fotmob.com/teams/9826/overview/crystal-palace
A15: Jaïro Riedewald | B15: MD | C15: 2017/18 | D15: 2018/19 | E15: Minutes | F15: 0 | H15: Yes | I15: =IF(AND(H15="Yes",F15>0),"Yes","No") -> No | J15: User-provided FotMob | K15: https://www.fotmob.com/teams/9826/overview/crystal-palace | L15: 0-minute seasons do not count as seasons played.
A16: Jaïro Riedewald | B16: MD | C16: 2017/18 | D16: 2019/20 | E16: Minutes | F16: 764 | G16: 6.33 | H16: Yes | I16: =IF(AND(H16="Yes",F16>0),"Yes","No") -> Yes | J16: User-provided FotMob | K16: https://www.fotmob.com/teams/9826/overview/crystal-palace
A17: Jaïro Riedewald | B17: MD | C17: 2017/18 | D17: 2020/21 | E17: Minutes | F17: 1817 | G17: 6.52 | H17: Yes | I17: =IF(AND(H17="Yes",F17>0),"Yes","No") -> Yes | J17: User-provided FotMob | K17: https://www.fotmob.com/teams/9826/overview/crystal-palace
A18: Jaïro Riedewald | B18: MD | C18: 2017/18 | D18: 2021/22 | E18: Minutes | F18: 116 | G18: 6.27 | H18: Yes | I18: =IF(AND(H18="Yes",F18>0),"Yes","No") -> Yes | J18: User-provided FotMob | K18: https://www.fotmob.com/teams/9826/overview/crystal-palace
A19: Jaïro Riedewald | B19: MD | C19: 2017/18 | D19: 2022/23 | E19: Minutes | F19: 60 | G19: 6.6 | H19: Yes | I19: =IF(AND(H19="Yes",F19>0),"Yes","No") -> Yes | J19: User-provided FotMob | K19: https://www.fotmob.com/teams/9826/overview/crystal-palace
A20: Jaïro Riedewald | B20: MD | C20: 2017/18 | D20: 2023/24 | E20: Minutes | F20: 229 | G20: 6.41 | H20: Yes | I20: =IF(AND(H20="Yes",F20>0),"Yes","No") -> Yes | J20: User-provided FotMob | K20: https://www.fotmob.com/teams/9826/overview/crystal-palace
A21: Jarosław Jach | B21: DF | C21: 2017/18 | D21: 2017/18 | E21: Minutes | F21: 0 | H21: Yes | I21: =IF(AND(H21="Yes",F21>0),"Yes","No") -> No | J21: User-provided FotMob | K21: https://www.fotmob.com/teams/9826/overview/crystal-palace | L21: No Palace Premier League minutes.
A22: Diego Cavalieri | B22: GK | C22: 2017/18 | D22: 2017/18 | E22: Matches | F22: 0 | H22: Yes | I22: =IF(AND(H22="Yes",F22>0),"Yes","No") -> No | J22: User-provided FotMob | K22: https://www.fotmob.com/teams/9826/overview/crystal-palace | L22: No Palace Premier League appearances.
A23: Cheikhou Kouyaté | B23: MD | C23: 2018/19 | D23: 2018/19 | E23: Minutes | F23: 1897 | G23: 6.46 | H23: Yes | I23: =IF(AND(H23="Yes",F23>0),"Yes","No") -> Yes | J23: User-provided FotMob | K23: https://www.fotmob.com/teams/9826/overview/crystal-palace
A24: Cheikhou Kouyaté | B24: MD | C24: 2018/19 | D24: 2019/20 | E24: Minutes | F24: 2535 | G24: 6.58 | H24: Yes | I24: =IF(AND(H24="Yes",F24>0),"Yes","No") -> Yes | J24: User-provided FotMob | K24: https://www.fotmob.com/teams/9826/overview/crystal-palace
A25: Cheikhou Kouyaté | B25: MD | C25: 2018/19 | D25: 2020/21 | E25: Minutes | F25: 3123 | G25: 6.52 | H25: Yes | I25: =IF(AND(H25="Yes",F25>0),"Yes","No") -> Yes | J25: User-provided FotMob | K25: https://www.fotmob.com/teams/9826/overview/crystal-palace
A26: Cheikhou Kouyaté | B26: MD | C26: 2018/19 | D26: 2021/22 | E26: Minutes | F26: 1978 | G26: 6.99 | H26: Yes | I26: =IF(AND(H26="Yes",F26>0),"Yes","No") -> Yes | J26: User-provided FotMob | K26: https://www.fotmob.com/teams/9826/overview/crystal-palace
A27: Max Meyer | B27: MD | C27: 2018/19 | D27: 2018/19 | E27: Minutes | F27: 1410 | G27: 6.47 | H27: Yes | I27: =IF(AND(H27="Yes",F27>0),"Yes","No") -> Yes | J27: User-provided FotMob | K27: https://www.fotmob.com/teams/9826/overview/crystal-palace
A28: Max Meyer | B28: MD | C28: 2018/19 | D28: 2019/20 | E28: Minutes | F28: 650 | G28: 6.02 | H28: Yes | I28: =IF(AND(H28="Yes",F28>0),"Yes","No") -> Yes | J28: User-provided FotMob | K28: https://www.fotmob.com/teams/9826/overview/crystal-palace
A29: Max Meyer | B29: MD | C29: 2018/19 | D29: 2020/21 | E29: Minutes | F29: 0 | H29: Yes | I29: =IF(AND(H29="Yes",F29>0),"Yes","No") -> No | J29: User-provided FotMob | K29: https://www.fotmob.com/teams/9826/overview/crystal-palace | L29: 0-minute season does not count.
A30: Bakary Sako | B30: FW | C30: 2018/19 | D30: 2018/19 | E30: Minutes | F30: 26 | G30: 5.87 | H30: Yes | I30: =IF(AND(H30="Yes",F30>0),"Yes","No") -> Yes | J30: User-provided FotMob | K30: https://www.fotmob.com/teams/9826/overview/crystal-palace
A31: Vicente Guaita | B31: GK | C31: 2018/19 | D31: 2018/19 | E31: Matches | F31: 20 | G31: 6.44 | H31: Yes | I31: =IF(AND(H31="Yes",F31>0),"Yes","No") -> Yes | J31: User-provided FotMob | K31: https://www.fotmob.com/teams/9826/overview/crystal-palace
A32: Vicente Guaita | B32: GK | C32: 2018/19 | D32: 2019/20 | E32: Matches | F32: 35 | G32: 6.46 | H32: Yes | I32: =IF(AND(H32="Yes",F32>0),"Yes","No") -> Yes | J32: User-provided FotMob | K32: https://www.fotmob.com/teams/9826/overview/crystal-palace
A33: Vicente Guaita | B33: GK | C33: 2018/19 | D33: 2020/21 | E33: Matches | F33: 37 | G33: 6.13 | H33: Yes | I33: =IF(AND(H33="Yes",F33>0),"Yes","No") -> Yes | J33: User-provided FotMob | K33: https://www.fotmob.com/teams/9826/overview/crystal-palace
A34: Vicente Guaita | B34: GK | C34: 2018/19 | D34: 2021/22 | E34: Matches | F34: 30 | G34: 6.65 | H34: Yes | I34: =IF(AND(H34="Yes",F34>0),"Yes","No") -> Yes | J34: User-provided FotMob | K34: https://www.fotmob.com/teams/9826/overview/crystal-palace
A35: Vicente Guaita | B35: GK | C35: 2018/19 | D35: 2022/23 | E35: Matches | F35: 27 | G35: 6.66 | H35: Yes | I35: =IF(AND(H35="Yes",F35>0),"Yes","No") -> Yes | J35: User-provided FotMob | K35: https://www.fotmob.com/teams/9826/overview/crystal-palace
A36: James McCarthy | B36: MD | C36: 2019/20 | D36: 2019/20 | E36: Minutes | F36: 1672 | G36: 6.42 | H36: Yes | I36: =IF(AND(H36="Yes",F36>0),"Yes","No") -> Yes | J36: User-provided FotMob | K36: https://www.fotmob.com/teams/9826/overview/crystal-palace
A37: James McCarthy | B37: MD | C37: 2019/20 | D37: 2020/21 | E37: Minutes | F37: 823 | G37: 6.48 | H37: Yes | I37: =IF(AND(H37="Yes",F37>0),"Yes","No") -> Yes | J37: User-provided FotMob | K37: https://www.fotmob.com/teams/9826/overview/crystal-palace
A38: Jordan Ayew | B38: FW | C38: 2019/20 | D38: 2019/20 | E38: Minutes | F38: 3160 | G38: 6.48 | H38: Yes | I38: =IF(AND(H38="Yes",F38>0),"Yes","No") -> Yes | J38: User-provided FotMob | K38: https://www.fotmob.com/teams/9826/overview/crystal-palace | L38: The isolated 2024/25 Palace cameo is excluded as agreed.
A39: Jordan Ayew | B39: FW | C39: 2019/20 | D39: 2020/21 | E39: Minutes | F39: 2097 | G39: 6.38 | H39: Yes | I39: =IF(AND(H39="Yes",F39>0),"Yes","No") -> Yes | J39: User-provided FotMob | K39: https://www.fotmob.com/teams/9826/overview/crystal-palace | L39: The isolated 2024/25 Palace cameo is excluded as agreed.
A40: Jordan Ayew | B40: FW | C40: 2019/20 | D40: 2021/22 | E40: Minutes | F40: 2023 | G40: 6.75 | H40: Yes | I40: =IF(AND(H40="Yes",F40>0),"Yes","No") -> Yes | J40: User-provided FotMob | K40: https://www.fotmob.com/teams/9826/overview/crystal-palace | L40: The isolated 2024/25 Palace cameo is excluded as agreed.
A41: Jordan Ayew | B41: FW | C41: 2019/20 | D41: 2022/23 | E41: Minutes | F41: 2720 | G41: 6.84 | H41: Yes | I41: =IF(AND(H41="Yes",F41>0),"Yes","No") -> Yes | J41: User-provided FotMob | K41: https://www.fotmob.com/teams/9826/overview/crystal-palace | L41: The isolated 2024/25 Palace cameo is excluded as agreed.
A42: Jordan Ayew | B42: FW | C42: 2019/20 | D42: 2023/24 | E42: Minutes | F42: 2594 | G42: 7 | H42: Yes | I42: =IF(AND(H42="Yes",F42>0),"Yes","No") -> Yes | J42: User-provided FotMob | K42: https://www.fotmob.com/teams/9826/overview/crystal-palace | L42: The isolated 2024/25 Palace cameo is excluded as agreed.
A43: Gary Cahill | B43: DF | C43: 2019/20 | D43: 2019/20 | E43: Minutes | F43: 2168 | G43: 6.54 | H43: Yes | I43: =IF(AND(H43="Yes",F43>0),"Yes","No") -> Yes | J43: User-provided FotMob | K43: https://www.fotmob.com/teams/9826/overview/crystal-palace
A44: Gary Cahill | B44: DF | C44: 2019/20 | D44: 2020/21 | E44: Minutes | F44: 1800 | G44: 6.37 | H44: Yes | I44: =IF(AND(H44="Yes",F44>0),"Yes","No") -> Yes | J44: User-provided FotMob | K44: https://www.fotmob.com/teams/9826/overview/crystal-palace
A45: Stephen Henderson | B45: GK | C45: 2019/20 | D45: 2019/20 | E45: Matches | F45: 0 | H45: Yes | I45: =IF(AND(H45="Yes",F45>0),"Yes","No") -> No | J45: User-provided FotMob | K45: https://www.fotmob.com/teams/9826/overview/crystal-palace | L45: No Palace Premier League appearances.
A46: Eberechi Eze | B46: MD | C46: 2020/21 | D46: 2020/21 | E46: Minutes | F46: 2562 | G46: 6.92 | H46: Yes | I46: =IF(AND(H46="Yes",F46>0),"Yes","No") -> Yes | J46: User-provided FotMob | K46: https://www.fotmob.com/teams/9826/overview/crystal-palace
A47: Eberechi Eze | B47: MD | C47: 2020/21 | D47: 2021/22 | E47: Minutes | F47: 602 | G47: 6.85 | H47: Yes | I47: =IF(AND(H47="Yes",F47>0),"Yes","No") -> Yes | J47: User-provided FotMob | K47: https://www.fotmob.com/teams/9826/overview/crystal-palace
A48: Eberechi Eze | B48: MD | C48: 2020/21 | D48: 2022/23 | E48: Minutes | F48: 2642 | G48: 7.27 | H48: Yes | I48: =IF(AND(H48="Yes",F48>0),"Yes","No") -> Yes | J48: User-provided FotMob | K48: https://www.fotmob.com/teams/9826/overview/crystal-palace
A49: Eberechi Eze | B49: MD | C49: 2020/21 | D49: 2023/24 | E49: Minutes | F49: 2065 | G49: 7.6 | H49: Yes | I49: =IF(AND(H49="Yes",F49>0),"Yes","No") -> Yes | J49: User-provided FotMob | K49: https://www.fotmob.com/teams/9826/overview/crystal-palace
A50: Eberechi Eze | B50: MD | C50: 2020/21 | D50: 2024/25 | E50: Minutes | F50: 2600 | G50: 7.4 | H50: Yes | I50: =IF(AND(H50="Yes",F50>0),"Yes","No") -> Yes | J50: User-provided FotMob | K50: https://www.fotmob.com/teams/9826/overview/crystal-palace
A51: Jack Butland | B51: GK | C51: 2020/21 | D51: 2020/21 | E51: Matches | F51: 1 | G51: 6.38 | H51: Yes | I51: =IF(AND(H51="Yes",F51>0),"Yes","No") -> Yes | J51: User-provided FotMob | K51: https://www.fotmob.com/teams/9826/overview/crystal-palace
A52: Jack Butland | B52: GK | C52: 2020/21 | D52: 2021/22 | E52: Matches | F52: 9 | G52: 6.26 | H52: Yes | I52: =IF(AND(H52="Yes",F52>0),"Yes","No") -> Yes | J52: User-provided FotMob | K52: https://www.fotmob.com/teams/9826/overview/crystal-palace
A53: Nathaniel Clyne | B53: DF | C53: 2020/21 | D53: 2020/21 | E53: Minutes | F53: 1147 | G53: 6.37 | H53: Yes | I53: =IF(AND(H53="Yes",F53>0),"Yes","No") -> Yes | J53: User-provided FotMob | K53: https://www.fotmob.com/teams/9826/overview/crystal-palace
A54: Nathaniel Clyne | B54: DF | C54: 2020/21 | D54: 2021/22 | E54: Minutes | F54: 1351 | G54: 6.97 | H54: Yes | I54: =IF(AND(H54="Yes",F54>0),"Yes","No") -> Yes | J54: User-provided FotMob | K54: https://www.fotmob.com/teams/9826/overview/crystal-palace
A55: Nathaniel Clyne | B55: DF | C55: 2020/21 | D55: 2022/23 | E55: Minutes | F55: 1642 | G55: 6.6 | H55: Yes | I55: =IF(AND(H55="Yes",F55>0),"Yes","No") -> Yes | J55: User-provided FotMob | K55: https://www.fotmob.com/teams/9826/overview/crystal-palace
A56: Nathaniel Clyne | B56: DF | C56: 2020/21 | D56: 2023/24 | E56: Minutes | F56: 1337 | G56: 6.82 | H56: Yes | I56: =IF(AND(H56="Yes",F56>0),"Yes","No") -> Yes | J56: User-provided FotMob | K56: https://www.fotmob.com/teams/9826/overview/crystal-palace
A57: Nathaniel Clyne | B57: DF | C57: 2020/21 | D57: 2024/25 | E57: Minutes | F57: 481 | G57: 6.22 | H57: Yes | I57: =IF(AND(H57="Yes",F57>0),"Yes","No") -> Yes | J57: User-provided FotMob | K57: https://www.fotmob.com/teams/9826/overview/crystal-palace
A58: Nathaniel Clyne | B58: DF | C58: 2020/21 | D58: 2025/26 | E58: Minutes | F58: 596 | G58: 6.68 | H58: Yes | I58: =IF(AND(H58="Yes",F58>0),"Yes","No") -> Yes | J58: User-provided FotMob | K58: https://www.fotmob.com/teams/9826/overview/crystal-palace
A59: Nathan Ferguson | B59: DF | C59: 2020/21 | D59: 2020/21 | E59: Minutes | F59: 0 | H59: Yes | I59: =IF(AND(H59="Yes",F59>0),"Yes","No") -> No | J59: User-provided FotMob | K59: https://www.fotmob.com/teams/9826/overview/crystal-palace
A60: Nathan Ferguson | B60: DF | C60: 2020/21 | D60: 2021/22 | E60: Minutes | F60: 8 | H60: Yes | I60: =IF(AND(H60="Yes",F60>0),"Yes","No") -> Yes | J60: User-provided FotMob | K60: https://www.fotmob.com/teams/9826/overview/crystal-palace | L60: FotMob did not publish a reliable season average for the eight-minute appearance.
A61: Nathan Ferguson | B61: DF | C61: 2020/21 | D61: 2022/23 | E61: Minutes | F61: 0 | H61: Yes | I61: =IF(AND(H61="Yes",F61>0),"Yes","No") -> No | J61: User-provided FotMob | K61: https://www.fotmob.com/teams/9826/overview/crystal-palace
A62: Nathan Ferguson | B62: DF | C62: 2020/21 | D62: 2023/24 | E62: Minutes | F62: 0 | H62: Yes | I62: =IF(AND(H62="Yes",F62>0),"Yes","No") -> No | J62: User-provided FotMob | K62: https://www.fotmob.com/teams/9826/overview/crystal-palace
A63: Marc Guéhi | B63: DF | C63: 2021/22 | D63: 2021/22 | E63: Minutes | F63: 3222 | G63: 7.04 | H63: Yes | I63: =IF(AND(H63="Yes",F63>0),"Yes","No") -> Yes | J63: User-provided FotMob | K63: https://www.fotmob.com/teams/9826/overview/crystal-palace | L63: Partial 2025/26 Palace spell excluded.
A64: Marc Guéhi | B64: DF | C64: 2021/22 | D64: 2022/23 | E64: Minutes | F64: 3329 | G64: 7.02 | H64: Yes | I64: =IF(AND(H64="Yes",F64>0),"Yes","No") -> Yes | J64: User-provided FotMob | K64: https://www.fotmob.com/teams/9826/overview/crystal-palace | L64: Partial 2025/26 Palace spell excluded.
A65: Marc Guéhi | B65: DF | C65: 2021/22 | D65: 2023/24 | E65: Minutes | F65: 2022 | G65: 6.79 | H65: Yes | I65: =IF(AND(H65="Yes",F65>0),"Yes","No") -> Yes | J65: User-provided FotMob | K65: https://www.fotmob.com/teams/9826/overview/crystal-palace | L65: Partial 2025/26 Palace spell excluded.
A66: Marc Guéhi | B66: DF | C66: 2021/22 | D66: 2024/25 | E66: Minutes | F66: 3059 | G66: 6.92 | H66: Yes | I66: =IF(AND(H66="Yes",F66>0),"Yes","No") -> Yes | J66: User-provided FotMob | K66: https://www.fotmob.com/teams/9826/overview/crystal-palace | L66: Partial 2025/26 Palace spell excluded.
A67: Joachim Andersen | B67: DF | C67: 2021/22 | D67: 2021/22 | E67: Minutes | F67: 2915 | G67: 6.91 | H67: Yes | I67: =IF(AND(H67="Yes",F67>0),"Yes","No") -> Yes | J67: FotMob via CraftedFC | K67: https://craftedfc.com/player-ratings/joachim-andersen
A68: Joachim Andersen | B68: DF | C68: 2021/22 | D68: 2022/23 | E68: Minutes | F68: 2783 | G68: 7.06 | H68: Yes | I68: =IF(AND(H68="Yes",F68>0),"Yes","No") -> Yes | J68: FotMob via CraftedFC | K68: https://craftedfc.com/player-ratings/joachim-andersen
A69: Joachim Andersen | B69: DF | C69: 2021/22 | D69: 2023/24 | E69: Minutes | F69: 3416 | G69: 7.03 | H69: Yes | I69: =IF(AND(H69="Yes",F69>0),"Yes","No") -> Yes | J69: FotMob via CraftedFC | K69: https://craftedfc.com/player-ratings/joachim-andersen
A70: Odsonne Édouard | B70: FW | C70: 2021/22 | D70: 2021/22 | E70: Minutes | F70: 1567 | G70: 6.78 | H70: Yes | I70: =IF(AND(H70="Yes",F70>0),"Yes","No") -> Yes | J70: FotMob via CraftedFC | K70: https://craftedfc.com/player-ratings/odsonne-edouard | L70: 2025/26 two-minute Palace appearance excluded; 2024/25 was at Leicester.
A71: Odsonne Édouard | B71: FW | C71: 2021/22 | D71: 2022/23 | E71: Minutes | F71: 1805 | G71: 6.43 | H71: Yes | I71: =IF(AND(H71="Yes",F71>0),"Yes","No") -> Yes | J71: FotMob via CraftedFC | K71: https://craftedfc.com/player-ratings/odsonne-edouard | L71: 2025/26 two-minute Palace appearance excluded; 2024/25 was at Leicester.
A72: Odsonne Édouard | B72: FW | C72: 2021/22 | D72: 2023/24 | E72: Minutes | F72: 1552 | G72: 6.75 | H72: Yes | I72: =IF(AND(H72="Yes",F72>0),"Yes","No") -> Yes | J72: FotMob via CraftedFC | K72: https://craftedfc.com/player-ratings/odsonne-edouard | L72: 2025/26 two-minute Palace appearance excluded; 2024/25 was at Leicester.
A73: Odsonne Édouard | B73: FW | C73: 2021/22 | D73: 2025/26 | E73: Minutes | F73: 2 | H73: No | I73: =IF(AND(H73="Yes",F73>0),"Yes","No") -> No | J73: FotMob via CraftedFC | K73: https://craftedfc.com/player-ratings/odsonne-edouard | L73: Excluded partial departure season.
A74: Jean-Philippe Mateta | B74: FW | C74: 2021/22 | D74: 2021/22 | E74: Minutes | F74: 1148 | G74: 6.6 | H74: Yes | I74: =IF(AND(H74="Yes",F74>0),"Yes","No") -> Yes | J74: FotMob via CraftedFC | K74: https://craftedfc.com/player-ratings/jean-philippe-mateta | L74: The pre-permanent 2020/21 loan season is excluded.
A75: Jean-Philippe Mateta | B75: FW | C75: 2021/22 | D75: 2022/23 | E75: Minutes | F75: 754 | G75: 6.15 | H75: Yes | I75: =IF(AND(H75="Yes",F75>0),"Yes","No") -> Yes | J75: FotMob via CraftedFC | K75: https://craftedfc.com/player-ratings/jean-philippe-mateta | L75: The pre-permanent 2020/21 loan season is excluded.
A76: Jean-Philippe Mateta | B76: FW | C76: 2021/22 | D76: 2023/24 | E76: Minutes | F76: 2283 | G76: 6.95 | H76: Yes | I76: =IF(AND(H76="Yes",F76>0),"Yes","No") -> Yes | J76: FotMob via CraftedFC | K76: https://craftedfc.com/player-ratings/jean-philippe-mateta | L76: The pre-permanent 2020/21 loan season is excluded.
A77: Jean-Philippe Mateta | B77: FW | C77: 2021/22 | D77: 2024/25 | E77: Minutes | F77: 2654 | G77: 6.86 | H77: Yes | I77: =IF(AND(H77="Yes",F77>0),"Yes","No") -> Yes | J77: FotMob via CraftedFC | K77: https://craftedfc.com/player-ratings/jean-philippe-mateta | L77: The pre-permanent 2020/21 loan season is excluded.
A78: Jean-Philippe Mateta | B78: FW | C78: 2021/22 | D78: 2025/26 | E78: Minutes | F78: 2222 | G78: 6.68 | H78: Yes | I78: =IF(AND(H78="Yes",F78>0),"Yes","No") -> Yes | J78: FotMob via CraftedFC | K78: https://craftedfc.com/player-ratings/jean-philippe-mateta | L78: The pre-permanent 2020/21 loan season is excluded.
A79: Michael Olise | B79: FW | C79: 2021/22 | D79: 2021/22 | E79: Minutes | F79: 1137 | G79: 6.95 | H79: Yes | I79: =IF(AND(H79="Yes",F79>0),"Yes","No") -> Yes | J79: FotMob via CraftedFC | K79: https://craftedfc.com/player-ratings/michael-olise
A80: Michael Olise | B80: FW | C80: 2021/22 | D80: 2022/23 | E80: Minutes | F80: 2756 | G80: 7.25 | H80: Yes | I80: =IF(AND(H80="Yes",F80>0),"Yes","No") -> Yes | J80: FotMob via CraftedFC | K80: https://craftedfc.com/player-ratings/michael-olise
A81: Michael Olise | B81: FW | C81: 2021/22 | D81: 2023/24 | E81: Minutes | F81: 1277 | G81: 7.71 | H81: Yes | I81: =IF(AND(H81="Yes",F81>0),"Yes","No") -> Yes | J81: FotMob via CraftedFC | K81: https://craftedfc.com/player-ratings/michael-olise
A82: Will Hughes | B82: MD | C82: 2021/22 | D82: 2021/22 | E82: Minutes | F82: 1058 | G82: 6.96 | H82: Yes | I82: =IF(AND(H82="Yes",F82>0),"Yes","No") -> Yes | J82: FotMob via CraftedFC | K82: https://craftedfc.com/player-ratings/will-hughes | L82: No season average was displayed for 2021/22.
A83: Will Hughes | B83: MD | C83: 2021/22 | D83: 2022/23 | E83: Minutes | F83: 827 | G83: 6.53 | H83: Yes | I83: =IF(AND(H83="Yes",F83>0),"Yes","No") -> Yes | J83: FotMob via CraftedFC | K83: https://craftedfc.com/player-ratings/will-hughes | L83: No season average was displayed for 2021/22.
A84: Will Hughes | B84: MD | C84: 2021/22 | D84: 2023/24 | E84: Minutes | F84: 1899 | G84: 6.78 | H84: Yes | I84: =IF(AND(H84="Yes",F84>0),"Yes","No") -> Yes | J84: FotMob via CraftedFC | K84: https://craftedfc.com/player-ratings/will-hughes | L84: No season average was displayed for 2021/22.
A85: Will Hughes | B85: MD | C85: 2021/22 | D85: 2024/25 | E85: Minutes | F85: 2118 | G85: 6.72 | H85: Yes | I85: =IF(AND(H85="Yes",F85>0),"Yes","No") -> Yes | J85: FotMob via CraftedFC | K85: https://craftedfc.com/player-ratings/will-hughes | L85: No season average was displayed for 2021/22.
A86: Will Hughes | B86: MD | C86: 2021/22 | D86: 2025/26 | E86: Minutes | F86: 1568 | G86: 6.56 | H86: Yes | I86: =IF(AND(H86="Yes",F86>0),"Yes","No") -> Yes | J86: FotMob via CraftedFC | K86: https://craftedfc.com/player-ratings/will-hughes | L86: No season average was displayed for 2021/22.
A87: Remi Matthews | B87: GK | C87: 2021/22 | D87: 2021/22 | E87: Matches | F87: 0 | H87: Yes | I87: =IF(AND(H87="Yes",F87>0),"Yes","No") -> No | J87: FotMob / official PL | K87: https://www.premierleague.com/en/players/169593/remi-matthews/overview
A88: Remi Matthews | B88: GK | C88: 2021/22 | D88: 2023/24 | E88: Matches | F88: 1 | H88: Yes | I88: =IF(AND(H88="Yes",F88>0),"Yes","No") -> Yes | J88: FotMob / official PL | K88: https://www.premierleague.com/en/players/169593/remi-matthews/overview | L88: 2022/23 loan season excluded. One Palace PL appearance came in 2023/24.
A89: Remi Matthews | B89: GK | C89: 2021/22 | D89: 2024/25 | E89: Matches | F89: 0 | H89: Yes | I89: =IF(AND(H89="Yes",F89>0),"Yes","No") -> No | J89: FotMob / official PL | K89: https://www.premierleague.com/en/players/169593/remi-matthews/overview
A90: Remi Matthews | B90: GK | C90: 2021/22 | D90: 2025/26 | E90: Matches | F90: 0 | H90: Yes | I90: =IF(AND(H90="Yes",F90>0),"Yes","No") -> No | J90: FotMob / official PL | K90: https://www.premierleague.com/en/players/169593/remi-matthews/overview
A91: Cheick Doucouré | B91: MD | C91: 2022/23 | D91: 2022/23 | E91: Minutes | F91: 2848 | G91: 7.12 | H91: Yes | I91: =IF(AND(H91="Yes",F91>0),"Yes","No") -> Yes | J91: FotMob / official usage backup | K91: https://www.fotmob.com/players/951954/cheick-oumar-doucoure
A92: Cheick Doucouré | B92: MD | C92: 2022/23 | D92: 2023/24 | E92: Minutes | F92: 920 | G92: 7.28 | H92: Yes | I92: =IF(AND(H92="Yes",F92>0),"Yes","No") -> Yes | J92: FotMob / official usage backup | K92: https://www.fotmob.com/players/951954/cheick-oumar-doucoure | L92: Later low-usage/injury seasons have no published season average.
A93: Cheick Doucouré | B93: MD | C93: 2022/23 | D93: 2024/25 | E93: Minutes | F93: 443 | G93: 6.53 | H93: Yes | I93: =IF(AND(H93="Yes",F93>0),"Yes","No") -> Yes | J93: FotMob / official usage backup | K93: https://www.fotmob.com/players/951954/cheick-oumar-doucoure | L93: Later low-usage/injury seasons have no published season average.
A94: Cheick Doucouré | B94: MD | C94: 2022/23 | D94: 2025/26 | E94: Minutes | F94: 0 | H94: Yes | I94: =IF(AND(H94="Yes",F94>0),"Yes","No") -> No | J94: FotMob / official usage backup | K94: https://www.fotmob.com/players/951954/cheick-oumar-doucoure | L94: Later low-usage/injury seasons have no published season average.
A95: Chris Richards | B95: DF | C95: 2022/23 | D95: 2022/23 | E95: Minutes | F95: 443 | G95: 6.7 | H95: Yes | I95: =IF(AND(H95="Yes",F95>0),"Yes","No") -> Yes | J95: FotMob via CraftedFC | K95: https://craftedfc.com/player-ratings/chris-richards
A96: Chris Richards | B96: DF | C96: 2022/23 | D96: 2023/24 | E96: Minutes | F96: 2091 | G96: 6.84 | H96: Yes | I96: =IF(AND(H96="Yes",F96>0),"Yes","No") -> Yes | J96: FotMob via CraftedFC | K96: https://craftedfc.com/player-ratings/chris-richards
A97: Chris Richards | B97: DF | C97: 2022/23 | D97: 2024/25 | E97: Minutes | F97: 1924 | G97: 6.68 | H97: Yes | I97: =IF(AND(H97="Yes",F97>0),"Yes","No") -> Yes | J97: FotMob via CraftedFC | K97: https://craftedfc.com/player-ratings/chris-richards
A98: Chris Richards | B98: DF | C98: 2022/23 | D98: 2025/26 | E98: Minutes | F98: 2826 | G98: 6.87 | H98: Yes | I98: =IF(AND(H98="Yes",F98>0),"Yes","No") -> Yes | J98: FotMob via CraftedFC | K98: https://craftedfc.com/player-ratings/chris-richards
A99: Naouirou Ahamada | B99: MD | C99: 2022/23 | D99: 2022/23 | E99: Minutes | F99: 87 | H99: Yes | I99: =IF(AND(H99="Yes",F99>0),"Yes","No") -> Yes | J99: FotMob / official usage backup | K99: https://www.fotmob.com/en-GB/players/1192854/naouirou-ahamada | L99: FotMob did not display a reliable Palace season average for the limited minutes.
A100: Naouirou Ahamada | B100: MD | C100: 2022/23 | D100: 2023/24 | E100: Minutes | F100: 332 | G100: 6.18 | H100: Yes | I100: =IF(AND(H100="Yes",F100>0),"Yes","No") -> Yes | J100: FotMob / official usage backup | K100: https://www.fotmob.com/en-GB/players/1192854/naouirou-ahamada | L100: FotMob did not display a reliable Palace season average for the limited minutes.
A101: Sam Johnstone | B101: GK | C101: 2022/23 | D101: 2022/23 | E101: Matches | F101: 9 | H101: Yes | I101: =IF(AND(H101="Yes",F101>0),"Yes","No") -> Yes | J101: FotMob / official PL | K101: https://www.fotmob.com/ | L101: Goalkeeper usage is measured in matches.
A102: Sam Johnstone | B102: GK | C102: 2022/23 | D102: 2023/24 | E102: Matches | F102: 20 | G102: 6.56 | H102: Yes | I102: =IF(AND(H102="Yes",F102>0),"Yes","No") -> Yes | J102: FotMob / official PL | K102: https://www.fotmob.com/ | L102: Goalkeeper usage is measured in matches.
...
